{"assets":{"03AC688E5349E9599517592F5190E17B":{"type":"texture","index":13,"assetRequest":{"type":"slide","state":"contents","slide":"none"},"url":{"native":"assets/2504B6EE-58FC-442B-8E49-4E0950B43FFB.pdf"},"width":137,"height":37},"B5220DA1F2F208804334271744E04F4F":{"type":"texture","index":3,"assetRequest":{"type":"slide","state":"contents","slide":"none"},"url":{"native":"assets/2504B6EE-58FC-442B-8E49-4E0950B43FFB.pdf"},"width":169,"height":112},"FDB0A57353609DDBB0262373DD1F00FC":{"type":"texture","index":14,"assetRequest":{"type":"slide","state":"contents","slide":"none"},"url":{"native":"assets/2504B6EE-58FC-442B-8E49-4E0950B43FFB.pdf"},"width":137,"height":37},"4DF62657AE554E4130461E4D80BD98EE":{"type":"texture","index":17,"assetRequest":{"type":"slide","state":"contents","slide":"none"},"url":{"native":"assets/2504B6EE-58FC-442B-8E49-4E0950B43FFB.pdf"},"width":960,"height":540},"A0FB76058FAC61A43D4CFF90B3D7596C":{"type":"texture","index":12,"assetRequest":{"type":"slide","state":"contents","slide":"none"},"url":{"native":"assets/2504B6EE-58FC-442B-8E49-4E0950B43FFB.pdf"},"width":137,"height":37},"8D7873D41F2F1E842D8E192A569B4856":{"type":"texture","index":16,"assetRequest":{"type":"slide","state":"contents","slide":"none"},"url":{"native":"assets/2504B6EE-58FC-442B-8E49-4E0950B43FFB.pdf"},"width":960,"height":540},"7EE671452877188CA169FB5E053CA3B6":{"type":"texture","index":10,"assetRequest":{"type":"slide","state":"contents","slide":"none"},"url":{"native":"assets/2504B6EE-58FC-442B-8E49-4E0950B43FFB.pdf"},"width":170,"height":35},"A4C77878657149918E38C17549010E14":{"type":"texture","index":4,"assetRequest":{"type":"slide","state":"contents","slide":"none"},"url":{"native":"assets/2504B6EE-58FC-442B-8E49-4E0950B43FFB.pdf"},"width":168,"height":111},"786DEEAFC23FA427E329DFED4DF6BBCD":{"type":"texture","index":1,"assetRequest":{"type":"slide","state":"contents","slide":"none"},"url":{"native":"assets/2504B6EE-58FC-442B-8E49-4E0950B43FFB.pdf"},"width":41,"height":36},"0CCB9AC07C019B0028F4FA1454740B24":{"type":"texture","index":7,"assetRequest":{"type":"slide","state":"contents","slide":"none"},"url":{"native":"assets/2504B6EE-58FC-442B-8E49-4E0950B43FFB.pdf"},"width":170,"height":77},"2E1A34E17231E452925A003E436365EB":{"type":"texture","index":8,"assetRequest":{"type":"slide","state":"contents","slide":"none"},"url":{"native":"assets/2504B6EE-58FC-442B-8E49-4E0950B43FFB.pdf"},"width":170,"height":35},"B469EC56385F729662076B2C0A3BEF85":{"type":"texture","index":9,"assetRequest":{"type":"slide","state":"contents","slide":"none"},"url":{"native":"assets/2504B6EE-58FC-442B-8E49-4E0950B43FFB.pdf"},"width":170,"height":35},"D099A78FB1EDE6891E557D5F1F9B90FC":{"type":"texture","index":5,"assetRequest":{"type":"slide","state":"contents","slide":"none"},"url":{"native":"assets/2504B6EE-58FC-442B-8E49-4E0950B43FFB.pdf"},"width":169,"height":112},"4E6D50A5EAE0F2E8CA7AE92962F2E365":{"type":"texture","index":2,"assetRequest":{"type":"slide","state":"contents","slide":"none"},"url":{"native":"assets/2504B6EE-58FC-442B-8E49-4E0950B43FFB.pdf"},"width":167,"height":111},"A787848A291ACEAD1980BED815CD552B":{"type":"texture","index":6,"assetRequest":{"type":"slide","state":"contents","slide":"none"},"url":{"native":"assets/2504B6EE-58FC-442B-8E49-4E0950B43FFB.pdf"},"width":170,"height":35},"7D652B3D8B8BD376EB6003073F6409C5":{"type":"texture","index":0,"assetRequest":{"type":"slide","state":"contents","slide":"none"},"url":{"native":"assets/2504B6EE-58FC-442B-8E49-4E0950B43FFB.pdf"},"width":960,"height":540},"BD71EF74E0A18D3088206F9DB91AD970":{"type":"texture","index":11,"assetRequest":{"type":"slide","state":"contents","slide":"none"},"url":{"native":"assets/2504B6EE-58FC-442B-8E49-4E0950B43FFB.pdf"},"width":138,"height":37},"840ACC901DCE90A7849E5B249BB38A42":{"type":"texture","index":15,"assetRequest":{"type":"slide","state":"contents","slide":"none"},"url":{"native":"assets/2504B6EE-58FC-442B-8E49-4E0950B43FFB.pdf"},"width":266,"height":55}},"events":[{"effects":[{"beginTime":0,"baseLayer":{"animations":[],"initialState":{"affineTransform":[1,0,0,1,0,0],"masksToBounds":false,"rotation":0,"scale":1,"position":{"pointX":97.15081977844238,"pointY":27.22496032714844},"width":46.05156326293945,"sublayerTransform":[1,0,0,0,0,1,0,0,0,0,1,0,0,0,0,1],"contentsRect":{"y":0,"x":0,"width":1,"height":1},"opacity":1,"edgeAntialiasingMask":251658240,"height":55.20000076293945,"hidden":false,"anchorPoint":{"pointX":0.5,"pointY":0.5}},"objectID":"0DBCCD6B-F5CE-4E50-A864-00C86A240629","layers":[{"animations":[],"initialState":{"affineTransform":[1,0,0,1,0,0],"masksToBounds":false,"rotation":0,"scale":1,"position":{"pointX":405.8749618530273,"pointY":270.3750400543213},"width":46.05156326293945,"sublayerTransform":[1,0,0,0,0,1,0,0,0,0,1,-0.0007001582493355197,0,0,0,1],"contentsRect":{"y":0,"x":0,"width":1,"height":1},"opacity":1,"edgeAntialiasingMask":251658240,"height":55.20000076293945,"hidden":false,"anchorPoint":{"pointX":8.813489338800798,"pointY":4.898098484010303}},"layers":[{"animations":[{"timeOffset":0,"beginTime":1e-100,"repeatCount":0,"animations":[{"timeOffset":0,"from":{"scalar":0},"beginTime":0,"repeatCount":0,"fillMode":"both","duration":0.5,"autoreverses":false,"timingFunction":"EaseInEaseOut","property":"opacity","to":{"scalar":1}},{"timeOffset":0,"from":{"scalar":false},"beginTime":0,"repeatCount":0,"fillMode":"forwards","property":"hidden","autoreverses":false,"duration":0.5,"to":{"scalar":false}}],"fillMode":"both","autoreverses":false,"duration":0.5}],"layers":[],"texturedRectangle":{"singleTextureOpacity":1,"textXHeight":0.7329644097222222,"textBaseline":0.9385405513975356,"isBackgroundTexture":true,"isVerticalText":false,"textColor":[0.9960785508155823,0.9960784316062927,0.9960784316062927,1],"textureType":6},"initialState":{"affineTransform":[1,0,0,1,0,0],"masksToBounds":false,"rotation":0,"scale":1,"position":{"pointX":22.37496185302734,"pointY":27.37504005432129},"width":41,"sublayerTransform":[1,0,0,0,0,1,0,0,0,0,1,0,0,0,0,1],"contentsRect":{"y":0,"x":0,"width":1,"height":1},"opacity":1,"edgeAntialiasingMask":0,"height":36,"hidden":true,"anchorPoint":{"pointX":0.5,"pointY":0.5}},"texture":"786DEEAFC23FA427E329DFED4DF6BBCD"}]}]},"effects":[{"beginTime":0,"baseLayer":{"animations":[],"initialState":{"affineTransform":[1,0,0,1,0,0],"masksToBounds":false,"rotation":0,"scale":1,"position":{"pointX":156.8272476196289,"pointY":260.678542137146},"width":166.6325988769531,"sublayerTransform":[1,0,0,0,0,1,0,0,0,0,1,0,0,0,0,1],"contentsRect":{"y":0,"x":0,"width":1,"height":1},"opacity":1,"edgeAntialiasingMask":251658240,"height":31.90023612976074,"hidden":false,"anchorPoint":{"pointX":0.5,"pointY":0.5}},"objectID":"2C047FAE-4F49-4BE9-8040-C3AA4DC00B56","layers":[{"animations":[],"initialState":{"affineTransform":[1,0,0,1,0,0],"masksToBounds":false,"rotation":0,"scale":1,"position":{"pointX":406.4890518188477,"pointY":25.27157592773438},"width":166.6325988769531,"sublayerTransform":[1,0,0,0,0,1,0,0,0,0,1,-0.0007001582493355197,0,0,0,1],"contentsRect":{"y":0,"x":0,"width":1,"height":1},"opacity":1,"edgeAntialiasingMask":251658240,"height":31.90023612976074,"hidden":false,"anchorPoint":{"pointX":2.439432947445129,"pointY":0.7922065474668296}},"layers":[{"animations":[{"timeOffset":0,"beginTime":1e-100,"repeatCount":0,"animations":[{"repeatCount":0,"timingControlPoint2y":1,"from":{"pointX":83.48905181884766,"pointY":-265.9568481445312},"timingFunction":"custom","timeOffset":0,"autoreverses":false,"timingControlPoint1x":0.4063220918178558,"fillMode":"both","property":"position","duration":0.5,"beginTime":0,"timingControlPoint2x":0.6016100645065308,"timingControlPoint1y":0.4998149275779724,"to":{"pointX":83.48905181884766,"pointY":15.77157592773438}},{"timeOffset":0,"from":{"scalar":false},"beginTime":0,"repeatCount":0,"fillMode":"forwards","property":"hidden","autoreverses":false,"duration":0.5,"to":{"scalar":false}}],"fillMode":"both","autoreverses":false,"duration":0.5}],"layers":[],"texturedRectangle":{"isBackgroundTexture":true,"singleTextureOpacity":1,"textureType":5,"textBaseline":0,"textXHeight":0,"isVerticalText":false},"initialState":{"affineTransform":[1,0,0,1,0,0],"masksToBounds":false,"rotation":0,"scale":1,"position":{"pointX":83.48905181884766,"pointY":15.77157592773438},"width":170,"sublayerTransform":[1,0,0,0,0,1,0,0,0,0,1,0,0,0,0,1],"contentsRect":{"y":0,"x":0,"width":1,"height":1},"opacity":1,"edgeAntialiasingMask":0,"height":35,"hidden":true,"anchorPoint":{"pointX":0.5,"pointY":0.5}},"texture":"A787848A291ACEAD1980BED815CD552B"}]}]},"effects":[{"beginTime":0,"baseLayer":{"animations":[],"initialState":{"affineTransform":[1,0,0,1,0,0],"masksToBounds":false,"rotation":0,"scale":1,"position":{"pointX":157.2372817993164,"pointY":205.2020034790039},"width":165.8125152587891,"sublayerTransform":[1,0,0,0,0,1,0,0,0,0,1,0,0,0,0,1],"contentsRect":{"y":0,"x":0,"width":1,"height":1},"opacity":1,"edgeAntialiasingMask":251658240,"height":109.4362945556641,"hidden":false,"anchorPoint":{"pointX":0.5,"pointY":0.5}},"objectID":"CBDF143B-DCB4-4C03-A1B0-E0AD6E261AFB","layers":[{"animations":[],"initialState":{"affineTransform":[1,0,0,1,0,0],"masksToBounds":false,"rotation":0,"scale":1,"position":{"pointX":405.6689758300781,"pointY":119.5161437988281},"width":165.8125152587891,"sublayerTransform":[1,0,0,0,0,1,0,0,0,0,1,-0.0007001582493355197,0,0,0,1],"contentsRect":{"y":0,"x":0,"width":1,"height":1},"opacity":1,"edgeAntialiasingMask":251658240,"height":109.4362945556641,"hidden":false,"anchorPoint":{"pointX":2.446552211073677,"pointY":1.092107004208161}},"layers":[{"animations":[{"timeOffset":0,"beginTime":1e-100,"repeatCount":0,"animations":[{"timeOffset":0,"from":{"scalar":0},"beginTime":0,"repeatCount":0,"fillMode":"both","duration":0.5,"autoreverses":false,"timingFunction":"EaseInEaseOut","property":"opacity","to":{"scalar":1}},{"timeOffset":0,"from":{"scalar":false},"beginTime":0,"repeatCount":0,"fillMode":"forwards","property":"hidden","autoreverses":false,"duration":0.5,"to":{"scalar":false}}],"fillMode":"both","autoreverses":false,"duration":0.5}],"layers":[],"texturedRectangle":{"isBackgroundTexture":true,"singleTextureOpacity":1,"textureType":5,"textBaseline":0,"textXHeight":0,"isVerticalText":false},"initialState":{"affineTransform":[1,0,0,1,0,0],"masksToBounds":false,"rotation":0,"scale":1,"position":{"pointX":83.16897583007812,"pointY":54.51614379882812},"width":169,"sublayerTransform":[1,0,0,0,0,1,0,0,0,0,1,0,0,0,0,1],"contentsRect":{"y":0,"x":0,"width":1,"height":1},"opacity":1,"edgeAntialiasingMask":0,"height":112,"hidden":true,"anchorPoint":{"pointX":0.5,"pointY":0.5}},"texture":"D099A78FB1EDE6891E557D5F1F9B90FC"}]}]},"effects":[{"beginTime":0,"baseLayer":{"animations":[],"initialState":{"affineTransform":[1,0,0,1,0,0],"masksToBounds":false,"rotation":0,"scale":1,"position":{"pointX":156.9833068847656,"pointY":397.5914265094902},"width":187.0642547607422,"sublayerTransform":[1,0,0,0,0,1,0,0,0,0,1,0,0,0,0,1],"contentsRect":{"y":0,"x":0,"width":1,"height":1},"opacity":1,"edgeAntialiasingMask":251658240,"height":88.89275292132425,"hidden":false,"anchorPoint":{"pointX":0.5,"pointY":0.5}},"objectID":"5FDD1E2B-3DE5-46E0-B206-E43351F60B41","layers":[{"animations":[],"initialState":{"affineTransform":[1,0,0,1,0,0],"masksToBounds":false,"rotation":0,"scale":1,"position":{"pointX":416.5488204956055,"pointY":-83.14505004882812},"width":187.0642547607422,"sublayerTransform":[1,0,0,0,0,1,0,0,0,0,1,-0.0007001582493355197,0,0,0,1],"contentsRect":{"y":0,"x":0,"width":1,"height":1},"opacity":1,"edgeAntialiasingMask":251658240,"height":88.89275292132425,"hidden":false,"anchorPoint":{"pointX":2.226768663143994,"pointY":-0.935341153428073}},"layers":[{"animations":[{"timeOffset":0,"beginTime":1e-100,"repeatCount":0,"animations":[{"timeOffset":0,"from":{"scalar":0},"beginTime":0,"repeatCount":0,"fillMode":"both","duration":0.5,"autoreverses":false,"timingFunction":"EaseInEaseOut","property":"opacity","to":{"scalar":1}},{"timeOffset":0,"from":{"scalar":false},"beginTime":0,"repeatCount":0,"fillMode":"forwards","property":"hidden","autoreverses":false,"duration":0.5,"to":{"scalar":false}}],"fillMode":"both","autoreverses":false,"duration":0.5}],"layers":[],"texturedRectangle":{"singleTextureOpacity":1,"textXHeight":0.1090909090909091,"textBaseline":0.9458625734626472,"isBackgroundTexture":true,"isVerticalText":false,"textColor":[0.3499999642372131,0.3499999642372131,0.3499999642372131,1],"textureType":6},"initialState":{"affineTransform":[1,0,0,1,0,0],"masksToBounds":false,"rotation":0,"scale":1,"position":{"pointX":88.54882049560547,"pointY":45.35494995117188},"width":170,"sublayerTransform":[1,0,0,0,0,1,0,0,0,0,1,0,0,0,0,1],"contentsRect":{"y":0,"x":0,"width":1,"height":1},"opacity":1,"edgeAntialiasingMask":0,"height":77,"hidden":true,"anchorPoint":{"pointX":0.5,"pointY":0.5}},"texture":"0CCB9AC07C019B0028F4FA1454740B24"}]}]},"effects":[{"beginTime":0,"baseLayer":{"animations":[],"initialState":{"affineTransform":[1,0,0,1,0,0],"masksToBounds":false,"rotation":0,"scale":1,"position":{"pointX":365.1184234619141,"pointY":260.678542137146},"width":166.6325988769531,"sublayerTransform":[1,0,0,0,0,1,0,0,0,0,1,0,0,0,0,1],"contentsRect":{"y":0,"x":0,"width":1,"height":1},"opacity":1,"edgeAntialiasingMask":251658240,"height":31.90023612976074,"hidden":false,"anchorPoint":{"pointX":0.5,"pointY":0.5}},"objectID":"2B53286A-6C01-40AA-A4D8-1584AAAEB04A","layers":[{"animations":[],"initialState":{"affineTransform":[1,0,0,1,0,0],"masksToBounds":false,"rotation":0,"scale":1,"position":{"pointX":198.1978759765625,"pointY":25.27157592773438},"width":166.6325988769531,"sublayerTransform":[1,0,0,0,0,1,0,0,0,0,1,-0.0007001582493355197,0,0,0,1],"contentsRect":{"y":0,"x":0,"width":1,"height":1},"opacity":1,"edgeAntialiasingMask":251658240,"height":31.90023612976074,"hidden":false,"anchorPoint":{"pointX":1.189430383444467,"pointY":0.7922065474668296}},"layers":[{"animations":[{"timeOffset":0,"beginTime":1e-100,"repeatCount":0,"animations":[{"repeatCount":0,"timingControlPoint2y":1,"from":{"pointX":83.1978759765625,"pointY":-265.9568481445312},"timingFunction":"custom","timeOffset":0,"autoreverses":false,"timingControlPoint1x":0.4063220918178558,"fillMode":"both","property":"position","duration":0.5,"beginTime":0,"timingControlPoint2x":0.6016100645065308,"timingControlPoint1y":0.4998149275779724,"to":{"pointX":83.1978759765625,"pointY":15.77157592773438}},{"timeOffset":0,"from":{"scalar":false},"beginTime":0,"repeatCount":0,"fillMode":"forwards","property":"hidden","autoreverses":false,"duration":0.5,"to":{"scalar":false}}],"fillMode":"both","autoreverses":false,"duration":0.5}],"layers":[],"texturedRectangle":{"isBackgroundTexture":true,"singleTextureOpacity":1,"textureType":5,"textBaseline":0,"textXHeight":0,"isVerticalText":false},"initialState":{"affineTransform":[1,0,0,1,0,0],"masksToBounds":false,"rotation":0,"scale":1,"position":{"pointX":83.1978759765625,"pointY":15.77157592773438},"width":170,"sublayerTransform":[1,0,0,0,0,1,0,0,0,0,1,0,0,0,0,1],"contentsRect":{"y":0,"x":0,"width":1,"height":1},"opacity":1,"edgeAntialiasingMask":0,"height":35,"hidden":true,"anchorPoint":{"pointX":0.5,"pointY":0.5}},"texture":"2E1A34E17231E452925A003E436365EB"}]}]},"effects":[{"beginTime":0,"baseLayer":{"animations":[],"initialState":{"affineTransform":[1,0,0,1,0,0],"masksToBounds":false,"rotation":0,"scale":1,"position":{"pointX":364.057243347168,"pointY":200.614372253418},"width":164.5102386474609,"sublayerTransform":[1,0,0,0,0,1,0,0,0,0,1,0,0,0,0,1],"contentsRect":{"y":0,"x":0,"width":1,"height":1},"opacity":1,"edgeAntialiasingMask":251658240,"height":108.5558319091797,"hidden":false,"anchorPoint":{"pointX":0.5,"pointY":0.5}},"objectID":"8D6151BA-B7A8-4EDC-873C-43524B846B8D","layers":[{"animations":[],"initialState":{"affineTransform":[1,0,0,1,0,0],"masksToBounds":false,"rotation":0,"scale":1,"position":{"pointX":198.1978759765625,"pointY":123.6635437011719},"width":164.5102386474609,"sublayerTransform":[1,0,0,0,0,1,0,0,0,0,1,-0.0007001582493355197,0,0,0,1],"contentsRect":{"y":0,"x":0,"width":1,"height":1},"opacity":1,"edgeAntialiasingMask":251658240,"height":108.5558319091797,"hidden":false,"anchorPoint":{"pointX":1.204775323445326,"pointY":1.139169969280247}},"layers":[{"animations":[{"timeOffset":0,"beginTime":1e-100,"repeatCount":0,"animations":[{"timeOffset":0,"from":{"scalar":0},"beginTime":0,"repeatCount":0,"fillMode":"both","duration":0.5,"autoreverses":false,"timingFunction":"EaseInEaseOut","property":"opacity","to":{"scalar":1}},{"timeOffset":0,"from":{"scalar":false},"beginTime":0,"repeatCount":0,"fillMode":"forwards","property":"hidden","autoreverses":false,"duration":0.5,"to":{"scalar":false}}],"fillMode":"both","autoreverses":false,"duration":0.5}],"layers":[],"texturedRectangle":{"isBackgroundTexture":true,"singleTextureOpacity":1,"textureType":5,"textBaseline":0,"textXHeight":0,"isVerticalText":false},"initialState":{"affineTransform":[1,0,0,1,0,0],"masksToBounds":false,"rotation":0,"scale":1,"position":{"pointX":82.1978759765625,"pointY":54.16354370117188},"width":168,"sublayerTransform":[1,0,0,0,0,1,0,0,0,0,1,0,0,0,0,1],"contentsRect":{"y":0,"x":0,"width":1,"height":1},"opacity":1,"edgeAntialiasingMask":0,"height":111,"hidden":true,"anchorPoint":{"pointX":0.5,"pointY":0.5}},"texture":"A4C77878657149918E38C17549010E14"}]}]},"effects":[{"beginTime":0,"baseLayer":{"animations":[],"initialState":{"affineTransform":[1,0,0,1,0,0],"masksToBounds":false,"rotation":0,"scale":1,"position":{"pointX":365.1184310913086,"pointY":399.5577045856621},"width":187.0642547607422,"sublayerTransform":[1,0,0,0,0,1,0,0,0,0,1,0,0,0,0,1],"contentsRect":{"y":0,"x":0,"width":1,"height":1},"opacity":1,"edgeAntialiasingMask":251658240,"height":88.89275292132425,"hidden":false,"anchorPoint":{"pointX":0.5,"pointY":0.5}},"objectID":"E6D38246-2EAA-4518-B7D5-02C8C2968749","layers":[{"animations":[],"initialState":{"affineTransform":[1,0,0,1,0,0],"masksToBounds":false,"rotation":0,"scale":1,"position":{"pointX":208.4136962890625,"pointY":-85.111328125},"width":187.0642547607422,"sublayerTransform":[1,0,0,0,0,1,0,0,0,0,1,-0.0007001582493355197,0,0,0,1],"contentsRect":{"y":0,"x":0,"width":1,"height":1},"opacity":1,"edgeAntialiasingMask":251658240,"height":88.89275292132425,"hidden":false,"anchorPoint":{"pointX":1.114128920865328,"pointY":-0.9574608202350191}},"layers":[{"animations":[{"timeOffset":0,"beginTime":1e-100,"repeatCount":0,"animations":[{"timeOffset":0,"from":{"scalar":0},"beginTime":0,"repeatCount":0,"fillMode":"both","duration":0.5,"autoreverses":false,"timingFunction":"EaseInEaseOut","property":"opacity","to":{"scalar":1}},{"timeOffset":0,"from":{"scalar":false},"beginTime":0,"repeatCount":0,"fillMode":"forwards","property":"hidden","autoreverses":false,"duration":0.5,"to":{"scalar":false}}],"fillMode":"both","autoreverses":false,"duration":0.5}],"layers":[],"texturedRectangle":{"singleTextureOpacity":1,"textXHeight":0.1090909090909091,"textBaseline":0.9454246263999444,"isBackgroundTexture":true,"isVerticalText":false,"textColor":[0.3499999642372131,0.3499999642372131,0.3499999642372131,1],"textureType":6},"initialState":{"affineTransform":[1,0,0,1,0,0],"masksToBounds":false,"rotation":0,"scale":1,"position":{"pointX":88.4136962890625,"pointY":45.388671875},"width":170,"sublayerTransform":[1,0,0,0,0,1,0,0,0,0,1,0,0,0,0,1],"contentsRect":{"y":0,"x":0,"width":1,"height":1},"opacity":1,"edgeAntialiasingMask":0,"height":77,"hidden":true,"anchorPoint":{"pointX":0.5,"pointY":0.5}},"texture":"0CCB9AC07C019B0028F4FA1454740B24"}]}]},"effects":[{"beginTime":0,"baseLayer":{"animations":[],"initialState":{"affineTransform":[1,0,0,1,0,0],"masksToBounds":false,"rotation":0,"scale":1,"position":{"pointX":578.9833831787109,"pointY":259.9202690124512},"width":166.6325988769531,"sublayerTransform":[1,0,0,0,0,1,0,0,0,0,1,0,0,0,0,1],"contentsRect":{"y":0,"x":0,"width":1,"height":1},"opacity":1,"edgeAntialiasingMask":251658240,"height":31.90007781982422,"hidden":false,"anchorPoint":{"pointX":0.5,"pointY":0.5}},"objectID":"55D826A0-8150-4AC7-BF17-758AC7875AEA","layers":[{"animations":[],"initialState":{"affineTransform":[1,0,0,1,0,0],"masksToBounds":false,"rotation":0,"scale":1,"position":{"pointX":-15.66708374023438,"pointY":26.02976989746094},"width":166.6325988769531,"sublayerTransform":[1,0,0,0,0,1,0,0,0,0,1,-0.0007001582493355197,0,0,0,1],"contentsRect":{"y":0,"x":0,"width":1,"height":1},"opacity":1,"edgeAntialiasingMask":251658240,"height":31.90007781982422,"hidden":false,"anchorPoint":{"pointX":-0.09402172111474691,"pointY":0.8159782569961258}},"layers":[{"animations":[{"timeOffset":0,"beginTime":1e-100,"repeatCount":0,"animations":[{"repeatCount":0,"timingControlPoint2y":1,"from":{"pointX":83.33291625976562,"pointY":315.5297698974609},"timingFunction":"custom","timeOffset":0,"autoreverses":false,"timingControlPoint1x":0.4063220918178558,"fillMode":"both","property":"position","duration":0.5,"beginTime":0,"timingControlPoint2x":0.6016100645065308,"timingControlPoint1y":0.4998149275779724,"to":{"pointX":83.33291625976562,"pointY":15.52976989746094}},{"timeOffset":0,"from":{"scalar":false},"beginTime":0,"repeatCount":0,"fillMode":"forwards","property":"hidden","autoreverses":false,"duration":0.5,"to":{"scalar":false}}],"fillMode":"both","autoreverses":false,"duration":0.5}],"layers":[],"texturedRectangle":{"isBackgroundTexture":true,"singleTextureOpacity":1,"textureType":5,"textBaseline":0,"textXHeight":0,"isVerticalText":false},"initialState":{"affineTransform":[1,0,0,1,0,0],"masksToBounds":false,"rotation":0,"scale":1,"position":{"pointX":83.33291625976562,"pointY":15.52976989746094},"width":170,"sublayerTransform":[1,0,0,0,0,1,0,0,0,0,1,0,0,0,0,1],"contentsRect":{"y":0,"x":0,"width":1,"height":1},"opacity":1,"edgeAntialiasingMask":0,"height":35,"hidden":true,"anchorPoint":{"pointX":0.5,"pointY":0.5}},"texture":"B469EC56385F729662076B2C0A3BEF85"}]}]},"effects":[{"beginTime":0,"baseLayer":{"animations":[],"initialState":{"affineTransform":[1,0,0,1,0,0],"masksToBounds":false,"rotation":0,"scale":1,"position":{"pointX":578.5733413696289,"pointY":205.2020034790039},"width":165.8125152587891,"sublayerTransform":[1,0,0,0,0,1,0,0,0,0,1,0,0,0,0,1],"contentsRect":{"y":0,"x":0,"width":1,"height":1},"opacity":1,"edgeAntialiasingMask":251658240,"height":109.4362945556641,"hidden":false,"anchorPoint":{"pointX":0.5,"pointY":0.5}},"objectID":"DD959EB4-8D5C-4496-B66C-CAD37CC17321","layers":[{"animations":[],"initialState":{"affineTransform":[1,0,0,1,0,0],"masksToBounds":false,"rotation":0,"scale":1,"position":{"pointX":-15.66708374023438,"pointY":119.5161437988281},"width":165.8125152587891,"sublayerTransform":[1,0,0,0,0,1,0,0,0,0,1,-0.0007001582493355197,0,0,0,1],"contentsRect":{"y":0,"x":0,"width":1,"height":1},"opacity":1,"edgeAntialiasingMask":251658240,"height":109.4362945556641,"hidden":false,"anchorPoint":{"pointX":-0.0944867383248016,"pointY":1.092107004208161}},"layers":[{"animations":[{"timeOffset":0,"beginTime":1e-100,"repeatCount":0,"animations":[{"timeOffset":0,"from":{"scalar":0},"beginTime":0,"repeatCount":0,"fillMode":"both","duration":0.5,"autoreverses":false,"timingFunction":"EaseInEaseOut","property":"opacity","to":{"scalar":1}},{"timeOffset":0,"from":{"scalar":false},"beginTime":0,"repeatCount":0,"fillMode":"forwards","property":"hidden","autoreverses":false,"duration":0.5,"to":{"scalar":false}}],"fillMode":"both","autoreverses":false,"duration":0.5}],"layers":[],"texturedRectangle":{"isBackgroundTexture":true,"singleTextureOpacity":1,"textureType":5,"textBaseline":0,"textXHeight":0,"isVerticalText":false},"initialState":{"affineTransform":[1,0,0,1,0,0],"masksToBounds":false,"rotation":0,"scale":1,"position":{"pointX":82.83291625976562,"pointY":54.51614379882812},"width":169,"sublayerTransform":[1,0,0,0,0,1,0,0,0,0,1,0,0,0,0,1],"contentsRect":{"y":0,"x":0,"width":1,"height":1},"opacity":1,"edgeAntialiasingMask":0,"height":112,"hidden":true,"anchorPoint":{"pointX":0.5,"pointY":0.5}},"texture":"B5220DA1F2F208804334271744E04F4F"}]}]},"effects":[{"beginTime":0,"baseLayer":{"animations":[],"initialState":{"affineTransform":[1,0,0,1,0,0],"masksToBounds":false,"rotation":0,"scale":1,"position":{"pointX":579.139518737793,"pointY":399.8055073200371},"width":187.0642547607422,"sublayerTransform":[1,0,0,0,0,1,0,0,0,0,1,0,0,0,0,1],"contentsRect":{"y":0,"x":0,"width":1,"height":1},"opacity":1,"edgeAntialiasingMask":251658240,"height":88.89275292132425,"hidden":false,"anchorPoint":{"pointX":0.5,"pointY":0.5}},"objectID":"06E583E4-120F-4FFD-B0FE-7959428F913B","layers":[{"animations":[],"initialState":{"affineTransform":[1,0,0,1,0,0],"masksToBounds":false,"rotation":0,"scale":1,"position":{"pointX":-5.607391357421875,"pointY":-85.359130859375},"width":187.0642547607422,"sublayerTransform":[1,0,0,0,0,1,0,0,0,0,1,-0.0007001582493355197,0,0,0,1],"contentsRect":{"y":0,"x":0,"width":1,"height":1},"opacity":1,"edgeAntialiasingMask":251658240,"height":88.89275292132425,"hidden":false,"anchorPoint":{"pointX":-0.02997575012176328,"pointY":-0.9602484798161586}},"layers":[{"animations":[{"timeOffset":0,"beginTime":1e-100,"repeatCount":0,"animations":[{"timeOffset":0,"from":{"scalar":0},"beginTime":0,"repeatCount":0,"fillMode":"both","duration":0.5,"autoreverses":false,"timingFunction":"EaseInEaseOut","property":"opacity","to":{"scalar":1}},{"timeOffset":0,"from":{"scalar":false},"beginTime":0,"repeatCount":0,"fillMode":"forwards","property":"hidden","autoreverses":false,"duration":0.5,"to":{"scalar":false}}],"fillMode":"both","autoreverses":false,"duration":0.5}],"layers":[],"texturedRectangle":{"singleTextureOpacity":1,"textXHeight":0.1090909090909091,"textBaseline":0.9486428437294898,"isBackgroundTexture":true,"isVerticalText":false,"textColor":[0.3499999642372131,0.3499999642372131,0.3499999642372131,1],"textureType":6},"initialState":{"affineTransform":[1,0,0,1,0,0],"masksToBounds":false,"rotation":0,"scale":1,"position":{"pointX":88.39260864257812,"pointY":45.140869140625},"width":170,"sublayerTransform":[1,0,0,0,0,1,0,0,0,0,1,0,0,0,0,1],"contentsRect":{"y":0,"x":0,"width":1,"height":1},"opacity":1,"edgeAntialiasingMask":0,"height":77,"hidden":true,"anchorPoint":{"pointX":0.5,"pointY":0.5}},"texture":"0CCB9AC07C019B0028F4FA1454740B24"}]}]},"effects":[{"beginTime":0,"baseLayer":{"animations":[],"initialState":{"affineTransform":[1,0,0,1,0,0],"masksToBounds":false,"rotation":0,"scale":1,"position":{"pointX":801.0782623291016,"pointY":259.9201927185059},"width":166.6325988769531,"sublayerTransform":[1,0,0,0,0,1,0,0,0,0,1,0,0,0,0,1],"contentsRect":{"y":0,"x":0,"width":1,"height":1},"opacity":1,"edgeAntialiasingMask":251658240,"height":31.90007781982422,"hidden":false,"anchorPoint":{"pointX":0.5,"pointY":0.5}},"objectID":"097E47BF-A057-4E83-964C-BE685ACC7C9F","layers":[{"animations":[],"initialState":{"affineTransform":[1,0,0,1,0,0],"masksToBounds":false,"rotation":0,"scale":1,"position":{"pointX":-237.761962890625,"pointY":26.02984619140625},"width":166.6325988769531,"sublayerTransform":[1,0,0,0,0,1,0,0,0,0,1,-0.0007001582493355197,0,0,0,1],"contentsRect":{"y":0,"x":0,"width":1,"height":1},"opacity":1,"edgeAntialiasingMask":251658240,"height":31.90007781982422,"hidden":false,"anchorPoint":{"pointX":-1.426863437845053,"pointY":0.815980648650019}},"layers":[{"animations":[{"timeOffset":0,"beginTime":1e-100,"repeatCount":0,"animations":[{"repeatCount":0,"timingControlPoint2y":1,"from":{"pointX":83.238037109375,"pointY":315.5298461914062},"timingFunction":"custom","timeOffset":0,"autoreverses":false,"timingControlPoint1x":0.4063220918178558,"fillMode":"both","property":"position","duration":0.5,"beginTime":0,"timingControlPoint2x":0.6016100645065308,"timingControlPoint1y":0.4998149275779724,"to":{"pointX":83.238037109375,"pointY":15.52984619140625}},{"timeOffset":0,"from":{"scalar":false},"beginTime":0,"repeatCount":0,"fillMode":"forwards","property":"hidden","autoreverses":false,"duration":0.5,"to":{"scalar":false}}],"fillMode":"both","autoreverses":false,"duration":0.5}],"layers":[],"texturedRectangle":{"isBackgroundTexture":true,"singleTextureOpacity":1,"textureType":5,"textBaseline":0,"textXHeight":0,"isVerticalText":false},"initialState":{"affineTransform":[1,0,0,1,0,0],"masksToBounds":false,"rotation":0,"scale":1,"position":{"pointX":83.238037109375,"pointY":15.52984619140625},"width":170,"sublayerTransform":[1,0,0,0,0,1,0,0,0,0,1,0,0,0,0,1],"contentsRect":{"y":0,"x":0,"width":1,"height":1},"opacity":1,"edgeAntialiasingMask":0,"height":35,"hidden":true,"anchorPoint":{"pointX":0.5,"pointY":0.5}},"texture":"7EE671452877188CA169FB5E053CA3B6"}]}]},"effects":[{"beginTime":0,"baseLayer":{"animations":[],"initialState":{"affineTransform":[1,0,0,1,0,0],"masksToBounds":false,"rotation":0,"scale":1,"position":{"pointX":799.6096038818359,"pointY":200.614372253418},"width":163.6952819824219,"sublayerTransform":[1,0,0,0,0,1,0,0,0,0,1,0,0,0,0,1],"contentsRect":{"y":0,"x":0,"width":1,"height":1},"opacity":1,"edgeAntialiasingMask":251658240,"height":108.5558319091797,"hidden":false,"anchorPoint":{"pointX":0.5,"pointY":0.5}},"objectID":"ACEC1F29-C9D7-4732-BE5F-F8C30C081C44","layers":[{"animations":[],"initialState":{"affineTransform":[1,0,0,1,0,0],"masksToBounds":false,"rotation":0,"scale":1,"position":{"pointX":-237.761962890625,"pointY":123.6635437011719},"width":163.6952819824219,"sublayerTransform":[1,0,0,0,0,1,0,0,0,0,1,-0.0007001582493355197,0,0,0,1],"contentsRect":{"y":0,"x":0,"width":1,"height":1},"opacity":1,"edgeAntialiasingMask":251658240,"height":108.5558319091797,"hidden":false,"anchorPoint":{"pointX":-1.452466803020973,"pointY":1.139169969280247}},"layers":[{"animations":[{"timeOffset":0,"beginTime":1e-100,"repeatCount":0,"animations":[{"timeOffset":0,"from":{"scalar":0},"beginTime":0,"repeatCount":0,"fillMode":"both","duration":0.5,"autoreverses":false,"timingFunction":"EaseInEaseOut","property":"opacity","to":{"scalar":1}},{"timeOffset":0,"from":{"scalar":false},"beginTime":0,"repeatCount":0,"fillMode":"forwards","property":"hidden","autoreverses":false,"duration":0.5,"to":{"scalar":false}}],"fillMode":"both","autoreverses":false,"duration":0.5}],"layers":[],"texturedRectangle":{"isBackgroundTexture":true,"singleTextureOpacity":1,"textureType":5,"textBaseline":0,"textXHeight":0,"isVerticalText":false},"initialState":{"affineTransform":[1,0,0,1,0,0],"masksToBounds":false,"rotation":0,"scale":1,"position":{"pointX":81.738037109375,"pointY":54.16354370117188},"width":167,"sublayerTransform":[1,0,0,0,0,1,0,0,0,0,1,0,0,0,0,1],"contentsRect":{"y":0,"x":0,"width":1,"height":1},"opacity":1,"edgeAntialiasingMask":0,"height":111,"hidden":true,"anchorPoint":{"pointX":0.5,"pointY":0.5}},"texture":"4E6D50A5EAE0F2E8CA7AE92962F2E365"}]}]},"effects":[{"beginTime":0,"baseLayer":{"animations":[],"initialState":{"affineTransform":[1,0,0,1,0,0],"masksToBounds":false,"rotation":0,"scale":1,"position":{"pointX":810.4791488647461,"pointY":399.8055073200371},"width":187.0642547607422,"sublayerTransform":[1,0,0,0,0,1,0,0,0,0,1,0,0,0,0,1],"contentsRect":{"y":0,"x":0,"width":1,"height":1},"opacity":1,"edgeAntialiasingMask":251658240,"height":88.89275292132425,"hidden":false,"anchorPoint":{"pointX":0.5,"pointY":0.5}},"objectID":"374347F3-D92D-4AE3-8AAA-270E4B4D5455","layers":[{"animations":[],"initialState":{"affineTransform":[1,0,0,1,0,0],"masksToBounds":false,"rotation":0,"scale":1,"position":{"pointX":-236.947021484375,"pointY":-85.359130859375},"width":187.0642547607422,"sublayerTransform":[1,0,0,0,0,1,0,0,0,0,1,-0.0007001582493355197,0,0,0,1],"contentsRect":{"y":0,"x":0,"width":1,"height":1},"opacity":1,"edgeAntialiasingMask":251658240,"height":88.89275292132425,"hidden":false,"anchorPoint":{"pointX":-1.266661136235961,"pointY":-0.9602484798161586}},"layers":[{"animations":[{"timeOffset":0,"beginTime":1e-100,"repeatCount":0,"animations":[{"timeOffset":0,"from":{"scalar":0},"beginTime":0,"repeatCount":0,"fillMode":"both","duration":0.5,"autoreverses":false,"timingFunction":"EaseInEaseOut","property":"opacity","to":{"scalar":1}},{"timeOffset":0,"from":{"scalar":false},"beginTime":0,"repeatCount":0,"fillMode":"forwards","property":"hidden","autoreverses":false,"duration":0.5,"to":{"scalar":false}}],"fillMode":"both","autoreverses":false,"duration":0.5}],"layers":[],"texturedRectangle":{"singleTextureOpacity":1,"textXHeight":0.1090909090909091,"textBaseline":0.9486428437294898,"isBackgroundTexture":true,"isVerticalText":false,"textColor":[0.3499999642372131,0.3499999642372131,0.3499999642372131,1],"textureType":6},"initialState":{"affineTransform":[1,0,0,1,0,0],"masksToBounds":false,"rotation":0,"scale":1,"position":{"pointX":88.052978515625,"pointY":45.140869140625},"width":170,"sublayerTransform":[1,0,0,0,0,1,0,0,0,0,1,0,0,0,0,1],"contentsRect":{"y":0,"x":0,"width":1,"height":1},"opacity":1,"edgeAntialiasingMask":0,"height":77,"hidden":true,"anchorPoint":{"pointX":0.5,"pointY":0.5}},"texture":"0CCB9AC07C019B0028F4FA1454740B24"}]}]},"effects":[],"duration":0.5,"type":"buildIn","attributes":{"direction":11},"name":"apple:wipe","objectID":"374347F3-D92D-4AE3-8AAA-270E4B4D5455"},{"beginTime":0,"baseLayer":{"animations":[],"initialState":{"affineTransform":[1,0,0,1,0,0],"masksToBounds":false,"rotation":0,"scale":1,"position":{"pointX":137.0178756713867,"pointY":328.4450702667236},"width":134.0667724609375,"sublayerTransform":[1,0,0,0,0,1,0,0,0,0,1,0,0,0,0,1],"contentsRect":{"y":0,"x":0,"width":1,"height":1},"opacity":1,"edgeAntialiasingMask":251658240,"height":33.56543350219727,"hidden":false,"anchorPoint":{"pointX":0.5,"pointY":0.5}},"objectID":"2A965F28-33FD-42BA-B58D-E4A20BCD8875","layers":[{"animations":[],"initialState":{"affineTransform":[1,0,0,1,0,0],"masksToBounds":false,"rotation":0,"scale":1,"position":{"pointX":410.015510559082,"pointY":-41.662353515625},"width":134.0667724609375,"sublayerTransform":[1,0,0,0,0,1,0,0,0,0,1,-0.0007001582493355197,0,0,0,1],"contentsRect":{"y":0,"x":0,"width":1,"height":1},"opacity":1,"edgeAntialiasingMask":251658240,"height":33.56543350219727,"hidden":false,"anchorPoint":{"pointX":3.058293289476679,"pointY":-1.241227929110395}},"layers":[{"animations":[{"timeOffset":0,"beginTime":1e-100,"repeatCount":0,"animations":[{"repeatCount":0,"timingControlPoint2y":1,"from":{"pointX":67.01551055908203,"pointY":-333.82470703125},"timingFunction":"custom","timeOffset":0,"autoreverses":false,"timingControlPoint1x":0.4063220918178558,"fillMode":"both","property":"position","duration":0.5,"beginTime":0,"timingControlPoint2x":0.6016100645065308,"timingControlPoint1y":0.4998149275779724,"to":{"pointX":67.01551055908203,"pointY":16.837646484375}},{"timeOffset":0,"from":{"scalar":false},"beginTime":0,"repeatCount":0,"fillMode":"forwards","property":"hidden","autoreverses":false,"duration":0.5,"to":{"scalar":false}}],"fillMode":"both","autoreverses":false,"duration":0.5}],"layers":[],"texturedRectangle":{"isBackgroundTexture":true,"singleTextureOpacity":1,"textureType":5,"textBaseline":0,"textXHeight":0,"isVerticalText":false},"initialState":{"affineTransform":[1,0,0,1,0,0],"masksToBounds":false,"rotation":0,"scale":1,"position":{"pointX":67.01551055908203,"pointY":16.837646484375},"width":138,"sublayerTransform":[1,0,0,0,0,1,0,0,0,0,1,0,0,0,0,1],"contentsRect":{"y":0,"x":0,"width":1,"height":1},"opacity":1,"edgeAntialiasingMask":0,"height":37,"hidden":true,"anchorPoint":{"pointX":0.5,"pointY":0.5}},"texture":"BD71EF74E0A18D3088206F9DB91AD970"}]}]},"effects":[],"duration":0.5,"type":"buildIn","name":"apple:move in","objectID":"2A965F28-33FD-42BA-B58D-E4A20BCD8875"},{"beginTime":0,"baseLayer":{"animations":[],"initialState":{"affineTransform":[1,0,0,1,0,0],"masksToBounds":false,"rotation":0,"scale":1,"position":{"pointX":346.5858154296875,"pointY":328.4450702667236},"width":134.0667724609375,"sublayerTransform":[1,0,0,0,0,1,0,0,0,0,1,0,0,0,0,1],"contentsRect":{"y":0,"x":0,"width":1,"height":1},"opacity":1,"edgeAntialiasingMask":251658240,"height":33.56543350219727,"hidden":false,"anchorPoint":{"pointX":0.5,"pointY":0.5}},"objectID":"0A7FFB24-F636-4B2E-8E53-A694B4999BF8","layers":[{"animations":[],"initialState":{"affineTransform":[1,0,0,1,0,0],"masksToBounds":false,"rotation":0,"scale":1,"position":{"pointX":200.4475708007812,"pointY":-41.662353515625},"width":134.0667724609375,"sublayerTransform":[1,0,0,0,0,1,0,0,0,0,1,-0.0007001582493355197,0,0,0,1],"contentsRect":{"y":0,"x":0,"width":1,"height":1},"opacity":1,"edgeAntialiasingMask":251658240,"height":33.56543350219727,"hidden":false,"anchorPoint":{"pointX":1.495132366665908,"pointY":-1.241227929110395}},"layers":[{"animations":[{"timeOffset":0,"beginTime":1e-100,"repeatCount":0,"animations":[{"repeatCount":0,"timingControlPoint2y":1,"from":{"pointX":66.94757080078125,"pointY":-333.82470703125},"timingFunction":"custom","timeOffset":0,"autoreverses":false,"timingControlPoint1x":0.4063220918178558,"fillMode":"both","property":"position","duration":0.5,"beginTime":0,"timingControlPoint2x":0.6016100645065308,"timingControlPoint1y":0.4998149275779724,"to":{"pointX":66.94757080078125,"pointY":16.837646484375}},{"timeOffset":0,"from":{"scalar":false},"beginTime":0,"repeatCount":0,"fillMode":"forwards","property":"hidden","autoreverses":false,"duration":0.5,"to":{"scalar":false}}],"fillMode":"both","autoreverses":false,"duration":0.5}],"layers":[],"texturedRectangle":{"isBackgroundTexture":true,"singleTextureOpacity":1,"textureType":5,"textBaseline":0,"textXHeight":0,"isVerticalText":false},"initialState":{"affineTransform":[1,0,0,1,0,0],"masksToBounds":false,"rotation":0,"scale":1,"position":{"pointX":66.94757080078125,"pointY":16.837646484375},"width":137,"sublayerTransform":[1,0,0,0,0,1,0,0,0,0,1,0,0,0,0,1],"contentsRect":{"y":0,"x":0,"width":1,"height":1},"opacity":1,"edgeAntialiasingMask":0,"height":37,"hidden":true,"anchorPoint":{"pointX":0.5,"pointY":0.5}},"texture":"A0FB76058FAC61A43D4CFF90B3D7596C"}]}]},"effects":[],"duration":0.5,"type":"buildIn","name":"apple:move in","objectID":"0A7FFB24-F636-4B2E-8E53-A694B4999BF8"},{"beginTime":0,"baseLayer":{"animations":[],"initialState":{"affineTransform":[1,0,0,1,0,0],"masksToBounds":false,"rotation":0,"scale":1,"position":{"pointX":562.7004699707031,"pointY":328.4450702667236},"width":134.0667724609375,"sublayerTransform":[1,0,0,0,0,1,0,0,0,0,1,0,0,0,0,1],"contentsRect":{"y":0,"x":0,"width":1,"height":1},"opacity":1,"edgeAntialiasingMask":251658240,"height":33.56543350219727,"hidden":false,"anchorPoint":{"pointX":0.5,"pointY":0.5}},"objectID":"1909E330-6E47-4F2B-B717-E5A1CBEB8455","layers":[{"animations":[],"initialState":{"affineTransform":[1,0,0,1,0,0],"masksToBounds":false,"rotation":0,"scale":1,"position":{"pointX":-15.66708374023438,"pointY":-41.662353515625},"width":134.0667724609375,"sublayerTransform":[1,0,0,0,0,1,0,0,0,0,1,-0.0007001582493355197,0,0,0,1],"contentsRect":{"y":0,"x":0,"width":1,"height":1},"opacity":1,"edgeAntialiasingMask":251658240,"height":33.56543350219727,"hidden":false,"anchorPoint":{"pointX":-0.1168603036580091,"pointY":-1.241227929110395}},"layers":[{"animations":[{"timeOffset":0,"beginTime":1e-100,"repeatCount":0,"animations":[{"repeatCount":0,"timingControlPoint2y":1,"from":{"pointX":66.83291625976562,"pointY":-333.82470703125},"timingFunction":"custom","timeOffset":0,"autoreverses":false,"timingControlPoint1x":0.4063220918178558,"fillMode":"both","property":"position","duration":0.5,"beginTime":0,"timingControlPoint2x":0.6016100645065308,"timingControlPoint1y":0.4998149275779724,"to":{"pointX":66.83291625976562,"pointY":16.837646484375}},{"timeOffset":0,"from":{"scalar":false},"beginTime":0,"repeatCount":0,"fillMode":"forwards","property":"hidden","autoreverses":false,"duration":0.5,"to":{"scalar":false}}],"fillMode":"both","autoreverses":false,"duration":0.5}],"layers":[],"texturedRectangle":{"isBackgroundTexture":true,"singleTextureOpacity":1,"textureType":5,"textBaseline":0,"textXHeight":0,"isVerticalText":false},"initialState":{"affineTransform":[1,0,0,1,0,0],"masksToBounds":false,"rotation":0,"scale":1,"position":{"pointX":66.83291625976562,"pointY":16.837646484375},"width":137,"sublayerTransform":[1,0,0,0,0,1,0,0,0,0,1,0,0,0,0,1],"contentsRect":{"y":0,"x":0,"width":1,"height":1},"opacity":1,"edgeAntialiasingMask":0,"height":37,"hidden":true,"anchorPoint":{"pointX":0.5,"pointY":0.5}},"texture":"03AC688E5349E9599517592F5190E17B"}]}]},"effects":[],"duration":0.5,"type":"buildIn","name":"apple:move in","objectID":"1909E330-6E47-4F2B-B717-E5A1CBEB8455"},{"beginTime":0,"baseLayer":{"animations":[],"initialState":{"affineTransform":[1,0,0,1,0,0],"masksToBounds":false,"rotation":0,"scale":1,"position":{"pointX":784.7953491210938,"pointY":328.4450702667236},"width":134.0667724609375,"sublayerTransform":[1,0,0,0,0,1,0,0,0,0,1,0,0,0,0,1],"contentsRect":{"y":0,"x":0,"width":1,"height":1},"opacity":1,"edgeAntialiasingMask":251658240,"height":33.56543350219727,"hidden":false,"anchorPoint":{"pointX":0.5,"pointY":0.5}},"objectID":"C1EB0BCA-7A4B-4109-ACA8-E982B1049BF7","layers":[{"animations":[],"initialState":{"affineTransform":[1,0,0,1,0,0],"masksToBounds":false,"rotation":0,"scale":1,"position":{"pointX":-237.761962890625,"pointY":-41.662353515625},"width":134.0667724609375,"sublayerTransform":[1,0,0,0,0,1,0,0,0,0,1,-0.0007001582493355197,0,0,0,1],"contentsRect":{"y":0,"x":0,"width":1,"height":1},"opacity":1,"edgeAntialiasingMask":251658240,"height":33.56543350219727,"hidden":false,"anchorPoint":{"pointX":-1.773459288429583,"pointY":-1.241227929110395}},"layers":[{"animations":[{"timeOffset":0,"beginTime":1e-100,"repeatCount":0,"animations":[{"repeatCount":0,"timingControlPoint2y":1,"from":{"pointX":66.738037109375,"pointY":-333.82470703125},"timingFunction":"custom","timeOffset":0,"autoreverses":false,"timingControlPoint1x":0.4063220918178558,"fillMode":"both","property":"position","duration":0.5,"beginTime":0,"timingControlPoint2x":0.6016100645065308,"timingControlPoint1y":0.4998149275779724,"to":{"pointX":66.738037109375,"pointY":16.837646484375}},{"timeOffset":0,"from":{"scalar":false},"beginTime":0,"repeatCount":0,"fillMode":"forwards","property":"hidden","autoreverses":false,"duration":0.5,"to":{"scalar":false}}],"fillMode":"both","autoreverses":false,"duration":0.5}],"layers":[],"texturedRectangle":{"isBackgroundTexture":true,"singleTextureOpacity":1,"textureType":5,"textBaseline":0,"textXHeight":0,"isVerticalText":false},"initialState":{"affineTransform":[1,0,0,1,0,0],"masksToBounds":false,"rotation":0,"scale":1,"position":{"pointX":66.738037109375,"pointY":16.837646484375},"width":137,"sublayerTransform":[1,0,0,0,0,1,0,0,0,0,1,0,0,0,0,1],"contentsRect":{"y":0,"x":0,"width":1,"height":1},"opacity":1,"edgeAntialiasingMask":0,"height":37,"hidden":true,"anchorPoint":{"pointX":0.5,"pointY":0.5}},"texture":"FDB0A57353609DDBB0262373DD1F00FC"}]}]},"effects":[],"duration":0.5,"type":"buildIn","name":"apple:move in","objectID":"C1EB0BCA-7A4B-4109-ACA8-E982B1049BF7"}],"duration":0.5,"type":"buildIn","attributes":{"direction":14},"name":"apple:wipe","objectID":"ACEC1F29-C9D7-4732-BE5F-F8C30C081C44"}],"duration":0.5,"type":"buildIn","name":"apple:move in","objectID":"097E47BF-A057-4E83-964C-BE685ACC7C9F"}],"duration":0.5,"type":"buildIn","attributes":{"direction":11},"name":"apple:wipe","objectID":"06E583E4-120F-4FFD-B0FE-7959428F913B"}],"duration":0.5,"type":"buildIn","attributes":{"direction":14},"name":"apple:wipe","objectID":"DD959EB4-8D5C-4496-B66C-CAD37CC17321"}],"duration":0.5,"type":"buildIn","name":"apple:move in","objectID":"55D826A0-8150-4AC7-BF17-758AC7875AEA"}],"duration":0.5,"type":"buildIn","attributes":{"direction":11},"name":"apple:wipe","objectID":"E6D38246-2EAA-4518-B7D5-02C8C2968749"}],"duration":0.5,"type":"buildIn","attributes":{"direction":14},"name":"apple:wipe","objectID":"8D6151BA-B7A8-4EDC-873C-43524B846B8D"}],"duration":0.5,"type":"buildIn","name":"apple:move in","objectID":"2B53286A-6C01-40AA-A4D8-1584AAAEB04A"}],"duration":0.5,"type":"buildIn","attributes":{"direction":11},"name":"apple:wipe","objectID":"5FDD1E2B-3DE5-46E0-B206-E43351F60B41"}],"duration":0.5,"type":"buildIn","attributes":{"direction":14},"name":"apple:wipe","objectID":"CBDF143B-DCB4-4C03-A1B0-E0AD6E261AFB"}],"duration":0.5,"type":"buildIn","name":"apple:move in","objectID":"2C047FAE-4F49-4BE9-8040-C3AA4DC00B56"}],"duration":0.5,"type":"buildIn","name":"apple:dissolve character","objectID":"0DBCCD6B-F5CE-4E50-A864-00C86A240629"}],"automaticPlay":true,"hyperlinks":[],"accessibility":[{"text":"添加标题","targetRectangle":{"y":316.6277856826782,"x":742.7734560966492,"width":72,"height":25}},{"text":"产品四","targetRectangle":{"y":247.4201929361861,"x":774.0782623291016,"width":54,"height":25}},{"text":"产品一","targetRectangle":{"y":248.178541401152,"x":129.8272476196289,"width":54,"height":25}},{"text":"添加标题","targetRectangle":{"y":316.6277856826782,"x":520.6785769462585,"width":72,"height":25}},{"text":"产品三","targetRectangle":{"y":247.4202692301315,"x":551.9833831787109,"width":54,"height":25}},{"text":"04","targetRectangle":{"y":76.65866303443909,"x":94.06417417526245,"width":18,"height":23}},{"text":"点击输入标题 ","targetRectangle":{"y":65.95228338241577,"x":136.7823576927185,"width":200.890625,"height":45}},{"text":"添加标题","targetRectangle":{"y":316.6277856826782,"x":94.99598264694214,"width":72,"height":25}},{"text":"产品二","targetRectangle":{"y":248.178541401152,"x":338.1184234619141,"width":54,"height":25}},{"text":"添加标题","targetRectangle":{"y":316.6277856826782,"x":304.5639224052429,"width":72,"height":25}}],"baseLayer":{"animations":[],"initialState":{"affineTransform":[1,0,0,1,0,0],"masksToBounds":false,"rotation":0,"scale":1,"position":{"pointX":480,"pointY":270},"width":960,"sublayerTransform":[1,0,0,0,0,1,0,0,0,0,1,0,0,0,0,1],"contentsRect":{"y":0,"x":0,"width":1,"height":1},"opacity":1,"edgeAntialiasingMask":251658240,"height":540,"hidden":false,"anchorPoint":{"pointX":0.5,"pointY":0.5}},"layers":[{"animations":[],"initialState":{"affineTransform":[1,0,0,1,0,0],"masksToBounds":false,"rotation":0,"scale":1,"position":{"pointX":480,"pointY":270},"width":960,"sublayerTransform":[1,0,0,0,0,1,0,0,0,0,1,0,0,0,0,1],"contentsRect":{"y":0,"x":0,"width":1,"height":1},"opacity":1,"edgeAntialiasingMask":251658240,"height":540,"hidden":false,"anchorPoint":{"pointX":0.5,"pointY":0.5}},"layers":[{"animations":[],"initialState":{"affineTransform":[1,0,0,1,0,0],"masksToBounds":false,"rotation":0,"scale":1,"position":{"pointX":480,"pointY":270},"width":960,"sublayerTransform":[1,0,0,0,0,1,0,0,0,0,1,0,0,0,0,1],"contentsRect":{"y":0,"x":0,"width":1,"height":1},"opacity":1,"edgeAntialiasingMask":251658240,"height":540,"hidden":false,"anchorPoint":{"pointX":0.5,"pointY":0.5}},"layers":[{"animations":[],"layers":[],"texturedRectangle":{"isBackgroundTexture":true,"singleTextureOpacity":1,"textureType":1,"textBaseline":0,"textXHeight":0,"isVerticalText":false},"initialState":{"affineTransform":[1,0,0,1,0,0],"masksToBounds":false,"rotation":0,"scale":1,"position":{"pointX":480,"pointY":270},"width":960,"sublayerTransform":[1,0,0,0,0,1,0,0,0,0,1,0,0,0,0,1],"contentsRect":{"y":0,"x":0,"width":1,"height":1},"opacity":1,"edgeAntialiasingMask":0,"height":540,"hidden":false,"anchorPoint":{"pointX":0.5,"pointY":0.5}},"texture":"7D652B3D8B8BD376EB6003073F6409C5"}]}]},{"animations":[],"initialState":{"affineTransform":[1,0,0,1,0,0],"masksToBounds":false,"rotation":0,"scale":1,"position":{"pointX":480,"pointY":270},"width":960,"sublayerTransform":[1,0,0,0,0,1,0,0,0,0,1,0,0,0,0,1],"contentsRect":{"y":0,"x":0,"width":1,"height":1},"opacity":1,"edgeAntialiasingMask":251658240,"height":540,"hidden":false,"anchorPoint":{"pointX":0.5,"pointY":0.5}},"layers":[{"animations":[],"initialState":{"affineTransform":[1,0,0,1,0,0],"masksToBounds":false,"rotation":0,"scale":1,"position":{"pointX":97.15081977844238,"pointY":27.22496032714844},"width":46.05156326293945,"sublayerTransform":[1,0,0,0,0,1,0,0,0,0,1,0,0,0,0,1],"contentsRect":{"y":0,"x":0,"width":1,"height":1},"opacity":1,"edgeAntialiasingMask":251658240,"height":55.20000076293945,"hidden":false,"anchorPoint":{"pointX":0.5,"pointY":0.5}},"objectID":"0DBCCD6B-F5CE-4E50-A864-00C86A240629","layers":[{"animations":[],"layers":[],"texturedRectangle":{"singleTextureOpacity":1,"textXHeight":0.7329644097222222,"textBaseline":0.9385405513975356,"isBackgroundTexture":true,"isVerticalText":false,"textColor":[0.9960785508155823,0.9960784316062927,0.9960784316062927,1],"textureType":6},"initialState":{"affineTransform":[1,0,0,1,0,0],"masksToBounds":false,"rotation":0,"scale":1,"position":{"pointX":22.37496185302734,"pointY":27.37504005432129},"width":41,"sublayerTransform":[1,0,0,0,0,1,0,0,0,0,1,0,0,0,0,1],"contentsRect":{"y":0,"x":0,"width":1,"height":1},"opacity":1,"edgeAntialiasingMask":0,"height":36,"hidden":true,"anchorPoint":{"pointX":0.5,"pointY":0.5}},"texture":"786DEEAFC23FA427E329DFED4DF6BBCD"}]}]},{"animations":[],"initialState":{"affineTransform":[1,0,0,1,0,0],"masksToBounds":false,"rotation":0,"scale":1,"position":{"pointX":480,"pointY":270},"width":960,"sublayerTransform":[1,0,0,0,0,1,0,0,0,0,1,0,0,0,0,1],"contentsRect":{"y":0,"x":0,"width":1,"height":1},"opacity":1,"edgeAntialiasingMask":251658240,"height":540,"hidden":false,"anchorPoint":{"pointX":0.5,"pointY":0.5}},"layers":[{"animations":[],"initialState":{"affineTransform":[1,0,0,1,0,0],"masksToBounds":false,"rotation":0,"scale":1,"position":{"pointX":799.6096038818359,"pointY":200.614372253418},"width":163.6952819824219,"sublayerTransform":[1,0,0,0,0,1,0,0,0,0,1,0,0,0,0,1],"contentsRect":{"y":0,"x":0,"width":1,"height":1},"opacity":1,"edgeAntialiasingMask":251658240,"height":108.5558319091797,"hidden":false,"anchorPoint":{"pointX":0.5,"pointY":0.5}},"objectID":"ACEC1F29-C9D7-4732-BE5F-F8C30C081C44","layers":[{"animations":[],"layers":[],"texturedRectangle":{"isBackgroundTexture":true,"singleTextureOpacity":1,"textureType":5,"textBaseline":0,"textXHeight":0,"isVerticalText":false},"initialState":{"affineTransform":[1,0,0,1,0,0],"masksToBounds":false,"rotation":0,"scale":1,"position":{"pointX":81.738037109375,"pointY":54.16354370117188},"width":167,"sublayerTransform":[1,0,0,0,0,1,0,0,0,0,1,0,0,0,0,1],"contentsRect":{"y":0,"x":0,"width":1,"height":1},"opacity":1,"edgeAntialiasingMask":0,"height":111,"hidden":true,"anchorPoint":{"pointX":0.5,"pointY":0.5}},"texture":"4E6D50A5EAE0F2E8CA7AE92962F2E365"}]}]},{"animations":[],"initialState":{"affineTransform":[1,0,0,1,0,0],"masksToBounds":false,"rotation":0,"scale":1,"position":{"pointX":480,"pointY":270},"width":960,"sublayerTransform":[1,0,0,0,0,1,0,0,0,0,1,0,0,0,0,1],"contentsRect":{"y":0,"x":0,"width":1,"height":1},"opacity":1,"edgeAntialiasingMask":251658240,"height":540,"hidden":false,"anchorPoint":{"pointX":0.5,"pointY":0.5}},"layers":[{"animations":[],"initialState":{"affineTransform":[1,0,0,1,0,0],"masksToBounds":false,"rotation":0,"scale":1,"position":{"pointX":578.5733413696289,"pointY":205.2020034790039},"width":165.8125152587891,"sublayerTransform":[1,0,0,0,0,1,0,0,0,0,1,0,0,0,0,1],"contentsRect":{"y":0,"x":0,"width":1,"height":1},"opacity":1,"edgeAntialiasingMask":251658240,"height":109.4362945556641,"hidden":false,"anchorPoint":{"pointX":0.5,"pointY":0.5}},"objectID":"DD959EB4-8D5C-4496-B66C-CAD37CC17321","layers":[{"animations":[],"layers":[],"texturedRectangle":{"isBackgroundTexture":true,"singleTextureOpacity":1,"textureType":5,"textBaseline":0,"textXHeight":0,"isVerticalText":false},"initialState":{"affineTransform":[1,0,0,1,0,0],"masksToBounds":false,"rotation":0,"scale":1,"position":{"pointX":82.83291625976562,"pointY":54.51614379882812},"width":169,"sublayerTransform":[1,0,0,0,0,1,0,0,0,0,1,0,0,0,0,1],"contentsRect":{"y":0,"x":0,"width":1,"height":1},"opacity":1,"edgeAntialiasingMask":0,"height":112,"hidden":true,"anchorPoint":{"pointX":0.5,"pointY":0.5}},"texture":"B5220DA1F2F208804334271744E04F4F"}]}]},{"animations":[],"initialState":{"affineTransform":[1,0,0,1,0,0],"masksToBounds":false,"rotation":0,"scale":1,"position":{"pointX":480,"pointY":270},"width":960,"sublayerTransform":[1,0,0,0,0,1,0,0,0,0,1,0,0,0,0,1],"contentsRect":{"y":0,"x":0,"width":1,"height":1},"opacity":1,"edgeAntialiasingMask":251658240,"height":540,"hidden":false,"anchorPoint":{"pointX":0.5,"pointY":0.5}},"layers":[{"animations":[],"initialState":{"affineTransform":[1,0,0,1,0,0],"masksToBounds":false,"rotation":0,"scale":1,"position":{"pointX":364.057243347168,"pointY":200.614372253418},"width":164.5102386474609,"sublayerTransform":[1,0,0,0,0,1,0,0,0,0,1,0,0,0,0,1],"contentsRect":{"y":0,"x":0,"width":1,"height":1},"opacity":1,"edgeAntialiasingMask":251658240,"height":108.5558319091797,"hidden":false,"anchorPoint":{"pointX":0.5,"pointY":0.5}},"objectID":"8D6151BA-B7A8-4EDC-873C-43524B846B8D","layers":[{"animations":[],"layers":[],"texturedRectangle":{"isBackgroundTexture":true,"singleTextureOpacity":1,"textureType":5,"textBaseline":0,"textXHeight":0,"isVerticalText":false},"initialState":{"affineTransform":[1,0,0,1,0,0],"masksToBounds":false,"rotation":0,"scale":1,"position":{"pointX":82.1978759765625,"pointY":54.16354370117188},"width":168,"sublayerTransform":[1,0,0,0,0,1,0,0,0,0,1,0,0,0,0,1],"contentsRect":{"y":0,"x":0,"width":1,"height":1},"opacity":1,"edgeAntialiasingMask":0,"height":111,"hidden":true,"anchorPoint":{"pointX":0.5,"pointY":0.5}},"texture":"A4C77878657149918E38C17549010E14"}]}]},{"animations":[],"initialState":{"affineTransform":[1,0,0,1,0,0],"masksToBounds":false,"rotation":0,"scale":1,"position":{"pointX":480,"pointY":270},"width":960,"sublayerTransform":[1,0,0,0,0,1,0,0,0,0,1,0,0,0,0,1],"contentsRect":{"y":0,"x":0,"width":1,"height":1},"opacity":1,"edgeAntialiasingMask":251658240,"height":540,"hidden":false,"anchorPoint":{"pointX":0.5,"pointY":0.5}},"layers":[{"animations":[],"initialState":{"affineTransform":[1,0,0,1,0,0],"masksToBounds":false,"rotation":0,"scale":1,"position":{"pointX":157.2372817993164,"pointY":205.2020034790039},"width":165.8125152587891,"sublayerTransform":[1,0,0,0,0,1,0,0,0,0,1,0,0,0,0,1],"contentsRect":{"y":0,"x":0,"width":1,"height":1},"opacity":1,"edgeAntialiasingMask":251658240,"height":109.4362945556641,"hidden":false,"anchorPoint":{"pointX":0.5,"pointY":0.5}},"objectID":"CBDF143B-DCB4-4C03-A1B0-E0AD6E261AFB","layers":[{"animations":[],"layers":[],"texturedRectangle":{"isBackgroundTexture":true,"singleTextureOpacity":1,"textureType":5,"textBaseline":0,"textXHeight":0,"isVerticalText":false},"initialState":{"affineTransform":[1,0,0,1,0,0],"masksToBounds":false,"rotation":0,"scale":1,"position":{"pointX":83.16897583007812,"pointY":54.51614379882812},"width":169,"sublayerTransform":[1,0,0,0,0,1,0,0,0,0,1,0,0,0,0,1],"contentsRect":{"y":0,"x":0,"width":1,"height":1},"opacity":1,"edgeAntialiasingMask":0,"height":112,"hidden":true,"anchorPoint":{"pointX":0.5,"pointY":0.5}},"texture":"D099A78FB1EDE6891E557D5F1F9B90FC"}]}]},{"animations":[],"initialState":{"affineTransform":[1,0,0,1,0,0],"masksToBounds":false,"rotation":0,"scale":1,"position":{"pointX":480,"pointY":270},"width":960,"sublayerTransform":[1,0,0,0,0,1,0,0,0,0,1,0,0,0,0,1],"contentsRect":{"y":0,"x":0,"width":1,"height":1},"opacity":1,"edgeAntialiasingMask":251658240,"height":540,"hidden":false,"anchorPoint":{"pointX":0.5,"pointY":0.5}},"layers":[{"animations":[],"initialState":{"affineTransform":[1,0,0,1,0,0],"masksToBounds":false,"rotation":0,"scale":1,"position":{"pointX":156.8272476196289,"pointY":260.678542137146},"width":166.6325988769531,"sublayerTransform":[1,0,0,0,0,1,0,0,0,0,1,0,0,0,0,1],"contentsRect":{"y":0,"x":0,"width":1,"height":1},"opacity":1,"edgeAntialiasingMask":251658240,"height":31.90023612976074,"hidden":false,"anchorPoint":{"pointX":0.5,"pointY":0.5}},"objectID":"2C047FAE-4F49-4BE9-8040-C3AA4DC00B56","layers":[{"animations":[],"layers":[],"texturedRectangle":{"isBackgroundTexture":true,"singleTextureOpacity":1,"textureType":5,"textBaseline":0,"textXHeight":0,"isVerticalText":false},"initialState":{"affineTransform":[1,0,0,1,0,0],"masksToBounds":false,"rotation":0,"scale":1,"position":{"pointX":83.48905181884766,"pointY":15.77157592773438},"width":170,"sublayerTransform":[1,0,0,0,0,1,0,0,0,0,1,0,0,0,0,1],"contentsRect":{"y":0,"x":0,"width":1,"height":1},"opacity":1,"edgeAntialiasingMask":0,"height":35,"hidden":true,"anchorPoint":{"pointX":0.5,"pointY":0.5}},"texture":"A787848A291ACEAD1980BED815CD552B"}]}]},{"animations":[],"initialState":{"affineTransform":[1,0,0,1,0,0],"masksToBounds":false,"rotation":0,"scale":1,"position":{"pointX":480,"pointY":270},"width":960,"sublayerTransform":[1,0,0,0,0,1,0,0,0,0,1,0,0,0,0,1],"contentsRect":{"y":0,"x":0,"width":1,"height":1},"opacity":1,"edgeAntialiasingMask":251658240,"height":540,"hidden":false,"anchorPoint":{"pointX":0.5,"pointY":0.5}},"layers":[{"animations":[],"initialState":{"affineTransform":[1,0,0,1,0,0],"masksToBounds":false,"rotation":0,"scale":1,"position":{"pointX":156.9833068847656,"pointY":397.5914265094902},"width":187.0642547607422,"sublayerTransform":[1,0,0,0,0,1,0,0,0,0,1,0,0,0,0,1],"contentsRect":{"y":0,"x":0,"width":1,"height":1},"opacity":1,"edgeAntialiasingMask":251658240,"height":88.89275292132425,"hidden":false,"anchorPoint":{"pointX":0.5,"pointY":0.5}},"objectID":"5FDD1E2B-3DE5-46E0-B206-E43351F60B41","layers":[{"animations":[],"layers":[],"texturedRectangle":{"singleTextureOpacity":1,"textXHeight":0.1090909090909091,"textBaseline":0.9458625734626472,"isBackgroundTexture":true,"isVerticalText":false,"textColor":[0.3499999642372131,0.3499999642372131,0.3499999642372131,1],"textureType":6},"initialState":{"affineTransform":[1,0,0,1,0,0],"masksToBounds":false,"rotation":0,"scale":1,"position":{"pointX":88.54882049560547,"pointY":45.35494995117188},"width":170,"sublayerTransform":[1,0,0,0,0,1,0,0,0,0,1,0,0,0,0,1],"contentsRect":{"y":0,"x":0,"width":1,"height":1},"opacity":1,"edgeAntialiasingMask":0,"height":77,"hidden":true,"anchorPoint":{"pointX":0.5,"pointY":0.5}},"texture":"0CCB9AC07C019B0028F4FA1454740B24"}]}]},{"animations":[],"initialState":{"affineTransform":[1,0,0,1,0,0],"masksToBounds":false,"rotation":0,"scale":1,"position":{"pointX":480,"pointY":270},"width":960,"sublayerTransform":[1,0,0,0,0,1,0,0,0,0,1,0,0,0,0,1],"contentsRect":{"y":0,"x":0,"width":1,"height":1},"opacity":1,"edgeAntialiasingMask":251658240,"height":540,"hidden":false,"anchorPoint":{"pointX":0.5,"pointY":0.5}},"layers":[{"animations":[],"initialState":{"affineTransform":[1,0,0,1,0,0],"masksToBounds":false,"rotation":0,"scale":1,"position":{"pointX":365.1184234619141,"pointY":260.678542137146},"width":166.6325988769531,"sublayerTransform":[1,0,0,0,0,1,0,0,0,0,1,0,0,0,0,1],"contentsRect":{"y":0,"x":0,"width":1,"height":1},"opacity":1,"edgeAntialiasingMask":251658240,"height":31.90023612976074,"hidden":false,"anchorPoint":{"pointX":0.5,"pointY":0.5}},"objectID":"2B53286A-6C01-40AA-A4D8-1584AAAEB04A","layers":[{"animations":[],"layers":[],"texturedRectangle":{"isBackgroundTexture":true,"singleTextureOpacity":1,"textureType":5,"textBaseline":0,"textXHeight":0,"isVerticalText":false},"initialState":{"affineTransform":[1,0,0,1,0,0],"masksToBounds":false,"rotation":0,"scale":1,"position":{"pointX":83.1978759765625,"pointY":15.77157592773438},"width":170,"sublayerTransform":[1,0,0,0,0,1,0,0,0,0,1,0,0,0,0,1],"contentsRect":{"y":0,"x":0,"width":1,"height":1},"opacity":1,"edgeAntialiasingMask":0,"height":35,"hidden":true,"anchorPoint":{"pointX":0.5,"pointY":0.5}},"texture":"2E1A34E17231E452925A003E436365EB"}]}]},{"animations":[],"initialState":{"affineTransform":[1,0,0,1,0,0],"masksToBounds":false,"rotation":0,"scale":1,"position":{"pointX":480,"pointY":270},"width":960,"sublayerTransform":[1,0,0,0,0,1,0,0,0,0,1,0,0,0,0,1],"contentsRect":{"y":0,"x":0,"width":1,"height":1},"opacity":1,"edgeAntialiasingMask":251658240,"height":540,"hidden":false,"anchorPoint":{"pointX":0.5,"pointY":0.5}},"layers":[{"animations":[],"initialState":{"affineTransform":[1,0,0,1,0,0],"masksToBounds":false,"rotation":0,"scale":1,"position":{"pointX":578.9833831787109,"pointY":259.9202690124512},"width":166.6325988769531,"sublayerTransform":[1,0,0,0,0,1,0,0,0,0,1,0,0,0,0,1],"contentsRect":{"y":0,"x":0,"width":1,"height":1},"opacity":1,"edgeAntialiasingMask":251658240,"height":31.90007781982422,"hidden":false,"anchorPoint":{"pointX":0.5,"pointY":0.5}},"objectID":"55D826A0-8150-4AC7-BF17-758AC7875AEA","layers":[{"animations":[],"layers":[],"texturedRectangle":{"isBackgroundTexture":true,"singleTextureOpacity":1,"textureType":5,"textBaseline":0,"textXHeight":0,"isVerticalText":false},"initialState":{"affineTransform":[1,0,0,1,0,0],"masksToBounds":false,"rotation":0,"scale":1,"position":{"pointX":83.33291625976562,"pointY":15.52976989746094},"width":170,"sublayerTransform":[1,0,0,0,0,1,0,0,0,0,1,0,0,0,0,1],"contentsRect":{"y":0,"x":0,"width":1,"height":1},"opacity":1,"edgeAntialiasingMask":0,"height":35,"hidden":true,"anchorPoint":{"pointX":0.5,"pointY":0.5}},"texture":"B469EC56385F729662076B2C0A3BEF85"}]}]},{"animations":[],"initialState":{"affineTransform":[1,0,0,1,0,0],"masksToBounds":false,"rotation":0,"scale":1,"position":{"pointX":480,"pointY":270},"width":960,"sublayerTransform":[1,0,0,0,0,1,0,0,0,0,1,0,0,0,0,1],"contentsRect":{"y":0,"x":0,"width":1,"height":1},"opacity":1,"edgeAntialiasingMask":251658240,"height":540,"hidden":false,"anchorPoint":{"pointX":0.5,"pointY":0.5}},"layers":[{"animations":[],"initialState":{"affineTransform":[1,0,0,1,0,0],"masksToBounds":false,"rotation":0,"scale":1,"position":{"pointX":801.0782623291016,"pointY":259.9201927185059},"width":166.6325988769531,"sublayerTransform":[1,0,0,0,0,1,0,0,0,0,1,0,0,0,0,1],"contentsRect":{"y":0,"x":0,"width":1,"height":1},"opacity":1,"edgeAntialiasingMask":251658240,"height":31.90007781982422,"hidden":false,"anchorPoint":{"pointX":0.5,"pointY":0.5}},"objectID":"097E47BF-A057-4E83-964C-BE685ACC7C9F","layers":[{"animations":[],"layers":[],"texturedRectangle":{"isBackgroundTexture":true,"singleTextureOpacity":1,"textureType":5,"textBaseline":0,"textXHeight":0,"isVerticalText":false},"initialState":{"affineTransform":[1,0,0,1,0,0],"masksToBounds":false,"rotation":0,"scale":1,"position":{"pointX":83.238037109375,"pointY":15.52984619140625},"width":170,"sublayerTransform":[1,0,0,0,0,1,0,0,0,0,1,0,0,0,0,1],"contentsRect":{"y":0,"x":0,"width":1,"height":1},"opacity":1,"edgeAntialiasingMask":0,"height":35,"hidden":true,"anchorPoint":{"pointX":0.5,"pointY":0.5}},"texture":"7EE671452877188CA169FB5E053CA3B6"}]}]},{"animations":[],"initialState":{"affineTransform":[1,0,0,1,0,0],"masksToBounds":false,"rotation":0,"scale":1,"position":{"pointX":480,"pointY":270},"width":960,"sublayerTransform":[1,0,0,0,0,1,0,0,0,0,1,0,0,0,0,1],"contentsRect":{"y":0,"x":0,"width":1,"height":1},"opacity":1,"edgeAntialiasingMask":251658240,"height":540,"hidden":false,"anchorPoint":{"pointX":0.5,"pointY":0.5}},"layers":[{"animations":[],"initialState":{"affineTransform":[1,0,0,1,0,0],"masksToBounds":false,"rotation":0,"scale":1,"position":{"pointX":579.139518737793,"pointY":399.8055073200371},"width":187.0642547607422,"sublayerTransform":[1,0,0,0,0,1,0,0,0,0,1,0,0,0,0,1],"contentsRect":{"y":0,"x":0,"width":1,"height":1},"opacity":1,"edgeAntialiasingMask":251658240,"height":88.89275292132425,"hidden":false,"anchorPoint":{"pointX":0.5,"pointY":0.5}},"objectID":"06E583E4-120F-4FFD-B0FE-7959428F913B","layers":[{"animations":[],"layers":[],"texturedRectangle":{"singleTextureOpacity":1,"textXHeight":0.1090909090909091,"textBaseline":0.9486428437294898,"isBackgroundTexture":true,"isVerticalText":false,"textColor":[0.3499999642372131,0.3499999642372131,0.3499999642372131,1],"textureType":6},"initialState":{"affineTransform":[1,0,0,1,0,0],"masksToBounds":false,"rotation":0,"scale":1,"position":{"pointX":88.39260864257812,"pointY":45.140869140625},"width":170,"sublayerTransform":[1,0,0,0,0,1,0,0,0,0,1,0,0,0,0,1],"contentsRect":{"y":0,"x":0,"width":1,"height":1},"opacity":1,"edgeAntialiasingMask":0,"height":77,"hidden":true,"anchorPoint":{"pointX":0.5,"pointY":0.5}},"texture":"0CCB9AC07C019B0028F4FA1454740B24"}]}]},{"animations":[],"initialState":{"affineTransform":[1,0,0,1,0,0],"masksToBounds":false,"rotation":0,"scale":1,"position":{"pointX":480,"pointY":270},"width":960,"sublayerTransform":[1,0,0,0,0,1,0,0,0,0,1,0,0,0,0,1],"contentsRect":{"y":0,"x":0,"width":1,"height":1},"opacity":1,"edgeAntialiasingMask":251658240,"height":540,"hidden":false,"anchorPoint":{"pointX":0.5,"pointY":0.5}},"layers":[{"animations":[],"initialState":{"affineTransform":[1,0,0,1,0,0],"masksToBounds":false,"rotation":0,"scale":1,"position":{"pointX":365.1184310913086,"pointY":399.5577045856621},"width":187.0642547607422,"sublayerTransform":[1,0,0,0,0,1,0,0,0,0,1,0,0,0,0,1],"contentsRect":{"y":0,"x":0,"width":1,"height":1},"opacity":1,"edgeAntialiasingMask":251658240,"height":88.89275292132425,"hidden":false,"anchorPoint":{"pointX":0.5,"pointY":0.5}},"objectID":"E6D38246-2EAA-4518-B7D5-02C8C2968749","layers":[{"animations":[],"layers":[],"texturedRectangle":{"singleTextureOpacity":1,"textXHeight":0.1090909090909091,"textBaseline":0.9454246263999444,"isBackgroundTexture":true,"isVerticalText":false,"textColor":[0.3499999642372131,0.3499999642372131,0.3499999642372131,1],"textureType":6},"initialState":{"affineTransform":[1,0,0,1,0,0],"masksToBounds":false,"rotation":0,"scale":1,"position":{"pointX":88.4136962890625,"pointY":45.388671875},"width":170,"sublayerTransform":[1,0,0,0,0,1,0,0,0,0,1,0,0,0,0,1],"contentsRect":{"y":0,"x":0,"width":1,"height":1},"opacity":1,"edgeAntialiasingMask":0,"height":77,"hidden":true,"anchorPoint":{"pointX":0.5,"pointY":0.5}},"texture":"0CCB9AC07C019B0028F4FA1454740B24"}]}]},{"animations":[],"initialState":{"affineTransform":[1,0,0,1,0,0],"masksToBounds":false,"rotation":0,"scale":1,"position":{"pointX":480,"pointY":270},"width":960,"sublayerTransform":[1,0,0,0,0,1,0,0,0,0,1,0,0,0,0,1],"contentsRect":{"y":0,"x":0,"width":1,"height":1},"opacity":1,"edgeAntialiasingMask":251658240,"height":540,"hidden":false,"anchorPoint":{"pointX":0.5,"pointY":0.5}},"layers":[{"animations":[],"initialState":{"affineTransform":[1,0,0,1,0,0],"masksToBounds":false,"rotation":0,"scale":1,"position":{"pointX":810.4791488647461,"pointY":399.8055073200371},"width":187.0642547607422,"sublayerTransform":[1,0,0,0,0,1,0,0,0,0,1,0,0,0,0,1],"contentsRect":{"y":0,"x":0,"width":1,"height":1},"opacity":1,"edgeAntialiasingMask":251658240,"height":88.89275292132425,"hidden":false,"anchorPoint":{"pointX":0.5,"pointY":0.5}},"objectID":"374347F3-D92D-4AE3-8AAA-270E4B4D5455","layers":[{"animations":[],"layers":[],"texturedRectangle":{"singleTextureOpacity":1,"textXHeight":0.1090909090909091,"textBaseline":0.9486428437294898,"isBackgroundTexture":true,"isVerticalText":false,"textColor":[0.3499999642372131,0.3499999642372131,0.3499999642372131,1],"textureType":6},"initialState":{"affineTransform":[1,0,0,1,0,0],"masksToBounds":false,"rotation":0,"scale":1,"position":{"pointX":88.052978515625,"pointY":45.140869140625},"width":170,"sublayerTransform":[1,0,0,0,0,1,0,0,0,0,1,0,0,0,0,1],"contentsRect":{"y":0,"x":0,"width":1,"height":1},"opacity":1,"edgeAntialiasingMask":0,"height":77,"hidden":true,"anchorPoint":{"pointX":0.5,"pointY":0.5}},"texture":"0CCB9AC07C019B0028F4FA1454740B24"}]}]},{"animations":[],"initialState":{"affineTransform":[1,0,0,1,0,0],"masksToBounds":false,"rotation":0,"scale":1,"position":{"pointX":480,"pointY":270},"width":960,"sublayerTransform":[1,0,0,0,0,1,0,0,0,0,1,0,0,0,0,1],"contentsRect":{"y":0,"x":0,"width":1,"height":1},"opacity":1,"edgeAntialiasingMask":251658240,"height":540,"hidden":false,"anchorPoint":{"pointX":0.5,"pointY":0.5}},"layers":[{"animations":[],"initialState":{"affineTransform":[1,0,0,1,0,0],"masksToBounds":false,"rotation":0,"scale":1,"position":{"pointX":137.0178756713867,"pointY":328.4450702667236},"width":134.0667724609375,"sublayerTransform":[1,0,0,0,0,1,0,0,0,0,1,0,0,0,0,1],"contentsRect":{"y":0,"x":0,"width":1,"height":1},"opacity":1,"edgeAntialiasingMask":251658240,"height":33.56543350219727,"hidden":false,"anchorPoint":{"pointX":0.5,"pointY":0.5}},"objectID":"2A965F28-33FD-42BA-B58D-E4A20BCD8875","layers":[{"animations":[],"layers":[],"texturedRectangle":{"isBackgroundTexture":true,"singleTextureOpacity":1,"textureType":5,"textBaseline":0,"textXHeight":0,"isVerticalText":false},"initialState":{"affineTransform":[1,0,0,1,0,0],"masksToBounds":false,"rotation":0,"scale":1,"position":{"pointX":67.01551055908203,"pointY":16.837646484375},"width":138,"sublayerTransform":[1,0,0,0,0,1,0,0,0,0,1,0,0,0,0,1],"contentsRect":{"y":0,"x":0,"width":1,"height":1},"opacity":1,"edgeAntialiasingMask":0,"height":37,"hidden":true,"anchorPoint":{"pointX":0.5,"pointY":0.5}},"texture":"BD71EF74E0A18D3088206F9DB91AD970"}]}]},{"animations":[],"initialState":{"affineTransform":[1,0,0,1,0,0],"masksToBounds":false,"rotation":0,"scale":1,"position":{"pointX":480,"pointY":270},"width":960,"sublayerTransform":[1,0,0,0,0,1,0,0,0,0,1,0,0,0,0,1],"contentsRect":{"y":0,"x":0,"width":1,"height":1},"opacity":1,"edgeAntialiasingMask":251658240,"height":540,"hidden":false,"anchorPoint":{"pointX":0.5,"pointY":0.5}},"layers":[{"animations":[],"initialState":{"affineTransform":[1,0,0,1,0,0],"masksToBounds":false,"rotation":0,"scale":1,"position":{"pointX":346.5858154296875,"pointY":328.4450702667236},"width":134.0667724609375,"sublayerTransform":[1,0,0,0,0,1,0,0,0,0,1,0,0,0,0,1],"contentsRect":{"y":0,"x":0,"width":1,"height":1},"opacity":1,"edgeAntialiasingMask":251658240,"height":33.56543350219727,"hidden":false,"anchorPoint":{"pointX":0.5,"pointY":0.5}},"objectID":"0A7FFB24-F636-4B2E-8E53-A694B4999BF8","layers":[{"animations":[],"layers":[],"texturedRectangle":{"isBackgroundTexture":true,"singleTextureOpacity":1,"textureType":5,"textBaseline":0,"textXHeight":0,"isVerticalText":false},"initialState":{"affineTransform":[1,0,0,1,0,0],"masksToBounds":false,"rotation":0,"scale":1,"position":{"pointX":66.94757080078125,"pointY":16.837646484375},"width":137,"sublayerTransform":[1,0,0,0,0,1,0,0,0,0,1,0,0,0,0,1],"contentsRect":{"y":0,"x":0,"width":1,"height":1},"opacity":1,"edgeAntialiasingMask":0,"height":37,"hidden":true,"anchorPoint":{"pointX":0.5,"pointY":0.5}},"texture":"A0FB76058FAC61A43D4CFF90B3D7596C"}]}]},{"animations":[],"initialState":{"affineTransform":[1,0,0,1,0,0],"masksToBounds":false,"rotation":0,"scale":1,"position":{"pointX":480,"pointY":270},"width":960,"sublayerTransform":[1,0,0,0,0,1,0,0,0,0,1,0,0,0,0,1],"contentsRect":{"y":0,"x":0,"width":1,"height":1},"opacity":1,"edgeAntialiasingMask":251658240,"height":540,"hidden":false,"anchorPoint":{"pointX":0.5,"pointY":0.5}},"layers":[{"animations":[],"initialState":{"affineTransform":[1,0,0,1,0,0],"masksToBounds":false,"rotation":0,"scale":1,"position":{"pointX":562.7004699707031,"pointY":328.4450702667236},"width":134.0667724609375,"sublayerTransform":[1,0,0,0,0,1,0,0,0,0,1,0,0,0,0,1],"contentsRect":{"y":0,"x":0,"width":1,"height":1},"opacity":1,"edgeAntialiasingMask":251658240,"height":33.56543350219727,"hidden":false,"anchorPoint":{"pointX":0.5,"pointY":0.5}},"objectID":"1909E330-6E47-4F2B-B717-E5A1CBEB8455","layers":[{"animations":[],"layers":[],"texturedRectangle":{"isBackgroundTexture":true,"singleTextureOpacity":1,"textureType":5,"textBaseline":0,"textXHeight":0,"isVerticalText":false},"initialState":{"affineTransform":[1,0,0,1,0,0],"masksToBounds":false,"rotation":0,"scale":1,"position":{"pointX":66.83291625976562,"pointY":16.837646484375},"width":137,"sublayerTransform":[1,0,0,0,0,1,0,0,0,0,1,0,0,0,0,1],"contentsRect":{"y":0,"x":0,"width":1,"height":1},"opacity":1,"edgeAntialiasingMask":0,"height":37,"hidden":true,"anchorPoint":{"pointX":0.5,"pointY":0.5}},"texture":"03AC688E5349E9599517592F5190E17B"}]}]},{"animations":[],"initialState":{"affineTransform":[1,0,0,1,0,0],"masksToBounds":false,"rotation":0,"scale":1,"position":{"pointX":480,"pointY":270},"width":960,"sublayerTransform":[1,0,0,0,0,1,0,0,0,0,1,0,0,0,0,1],"contentsRect":{"y":0,"x":0,"width":1,"height":1},"opacity":1,"edgeAntialiasingMask":251658240,"height":540,"hidden":false,"anchorPoint":{"pointX":0.5,"pointY":0.5}},"layers":[{"animations":[],"initialState":{"affineTransform":[1,0,0,1,0,0],"masksToBounds":false,"rotation":0,"scale":1,"position":{"pointX":784.7953491210938,"pointY":328.4450702667236},"width":134.0667724609375,"sublayerTransform":[1,0,0,0,0,1,0,0,0,0,1,0,0,0,0,1],"contentsRect":{"y":0,"x":0,"width":1,"height":1},"opacity":1,"edgeAntialiasingMask":251658240,"height":33.56543350219727,"hidden":false,"anchorPoint":{"pointX":0.5,"pointY":0.5}},"objectID":"C1EB0BCA-7A4B-4109-ACA8-E982B1049BF7","layers":[{"animations":[],"layers":[],"texturedRectangle":{"isBackgroundTexture":true,"singleTextureOpacity":1,"textureType":5,"textBaseline":0,"textXHeight":0,"isVerticalText":false},"initialState":{"affineTransform":[1,0,0,1,0,0],"masksToBounds":false,"rotation":0,"scale":1,"position":{"pointX":66.738037109375,"pointY":16.837646484375},"width":137,"sublayerTransform":[1,0,0,0,0,1,0,0,0,0,1,0,0,0,0,1],"contentsRect":{"y":0,"x":0,"width":1,"height":1},"opacity":1,"edgeAntialiasingMask":0,"height":37,"hidden":true,"anchorPoint":{"pointX":0.5,"pointY":0.5}},"texture":"FDB0A57353609DDBB0262373DD1F00FC"}]}]},{"animations":[],"initialState":{"affineTransform":[1,0,0,1,0,0],"masksToBounds":false,"rotation":0,"scale":1,"position":{"pointX":480,"pointY":270},"width":960,"sublayerTransform":[1,0,0,0,0,1,0,0,0,0,1,0,0,0,0,1],"contentsRect":{"y":0,"x":0,"width":1,"height":1},"opacity":1,"edgeAntialiasingMask":251658240,"height":540,"hidden":false,"anchorPoint":{"pointX":0.5,"pointY":0.5}},"layers":[{"animations":[],"initialState":{"affineTransform":[1,0,0,1,0,0],"masksToBounds":false,"rotation":0,"scale":1,"position":{"pointX":210.901611328125,"pointY":88.45228385925293},"width":262.7427368164062,"sublayerTransform":[1,0,0,0,0,1,0,0,0,0,1,0,0,0,0,1],"contentsRect":{"y":0,"x":0,"width":1,"height":1},"opacity":1,"edgeAntialiasingMask":251658240,"height":52.20000076293945,"hidden":false,"anchorPoint":{"pointX":0.5,"pointY":0.5}},"objectID":"BC7D87F0-C9C9-4955-9215-A44AC410F246","layers":[{"animations":[],"layers":[],"texturedRectangle":{"isBackgroundTexture":true,"singleTextureOpacity":1,"textureType":5,"textBaseline":0,"textXHeight":0,"isVerticalText":false},"initialState":{"affineTransform":[1,0,0,1,0,0],"masksToBounds":false,"rotation":0,"scale":1,"position":{"pointX":131.4697570800781,"pointY":26.1477165222168},"width":266,"sublayerTransform":[1,0,0,0,0,1,0,0,0,0,1,0,0,0,0,1],"contentsRect":{"y":0,"x":0,"width":1,"height":1},"opacity":1,"edgeAntialiasingMask":0,"height":55,"hidden":false,"anchorPoint":{"pointX":0.5,"pointY":0.5}},"texture":"840ACC901DCE90A7849E5B249BB38A42"}]}]}]}},{"effects":[{"beginTime":4,"baseLayer":{"animations":[],"initialState":{"affineTransform":[1,0,0,1,0,0],"masksToBounds":false,"rotation":0,"scale":1,"position":{"pointX":480,"pointY":270},"width":960,"sublayerTransform":[1,0,0,0,0,1,0,0,0,0,1,0,0,0,0,1],"contentsRect":{"y":0,"x":0,"width":1,"height":1},"opacity":1,"edgeAntialiasingMask":251658240,"height":540,"hidden":false,"anchorPoint":{"pointX":0.5,"pointY":0.5}},"objectID":"0","layers":[{"animations":[],"initialState":{"affineTransform":[1,0,0,1,0,0],"masksToBounds":false,"rotation":0,"scale":1,"position":{"pointX":480,"pointY":270},"width":960,"sublayerTransform":[1,0,0,0,0,1,0,0,0,0,1,-0.0007001582493355197,0,0,0,1],"contentsRect":{"y":0,"x":0,"width":1,"height":1},"opacity":1,"edgeAntialiasingMask":251658240,"height":540,"hidden":false,"anchorPoint":{"pointX":0.5,"pointY":0.5}},"layers":[{"animations":[],"layers":[],"texturedRectangle":{"isBackgroundTexture":false,"singleTextureOpacity":1,"textureType":0,"textBaseline":0,"textXHeight":0,"isVerticalText":false},"initialState":{"affineTransform":[1,0,0,1,0,0],"masksToBounds":false,"rotation":0,"scale":1,"position":{"pointX":480,"pointY":270},"width":960,"sublayerTransform":[1,0,0,0,0,1,0,0,0,0,1,0,0,0,0,1],"contentsRect":{"y":0,"x":0,"width":1,"height":1},"opacity":1,"edgeAntialiasingMask":0,"height":540,"hidden":false,"anchorPoint":{"pointX":0.5,"pointY":0.5}},"texture":"4DF62657AE554E4130461E4D80BD98EE"},{"animations":[{"timeOffset":0,"beginTime":0,"repeatCount":0,"animations":[{"timeOffset":0,"from":{"scalar":1},"beginTime":0,"repeatCount":0,"fillMode":"removed","property":"opacity","autoreverses":false,"duration":0.6000000238418579,"to":{"scalar":1}},{"timeOffset":0,"from":{"scalar":0},"beginTime":0.6000000238418579,"repeatCount":0,"fillMode":"removed","property":"opacity","autoreverses":false,"duration":0.6000000238418579,"to":{"scalar":0}}],"fillMode":"both","autoreverses":false,"duration":1.200000047683716}],"layers":[],"texturedRectangle":{"isBackgroundTexture":false,"singleTextureOpacity":1,"textureType":0,"textBaseline":0,"textXHeight":0,"isVerticalText":false},"initialState":{"affineTransform":[1,0,0,1,0,0],"masksToBounds":false,"rotation":0,"scale":1,"position":{"pointX":480,"pointY":270},"width":960,"sublayerTransform":[1,0,0,0,0,1,0,0,0,0,1,0,0,0,0,1],"contentsRect":{"y":0,"x":0,"width":1,"height":1},"opacity":1,"edgeAntialiasingMask":0,"height":540,"hidden":false,"anchorPoint":{"pointX":0.5,"pointY":0.5}},"texture":"8D7873D41F2F1E842D8E192A569B4856"},{"animations":[{"timeOffset":0,"beginTime":0,"repeatCount":0,"animations":[{"timeOffset":0,"from":{"scalar":0},"beginTime":0,"repeatCount":0,"fillMode":"removed","duration":0.6000000238418579,"autoreverses":false,"timingFunction":"EaseIn","property":"opacity","to":{"scalar":1}},{"timeOffset":0,"from":{"scalar":1},"beginTime":0.6000000238418579,"repeatCount":0,"fillMode":"removed","duration":0.6000000238418579,"autoreverses":false,"timingFunction":"EaseOut","property":"opacity","to":{"scalar":0}}],"fillMode":"both","autoreverses":false,"duration":1.200000047683716}],"initialState":{"affineTransform":[1,0,0,1,0,0],"scale":1,"rotation":0,"masksToBounds":false,"position":{"pointX":480,"pointY":270},"backgroundColor":[0,0,0,1],"width":960,"sublayerTransform":[1,0,0,0,0,1,0,0,0,0,1,0,0,0,0,1],"contentsRect":{"y":0,"x":0,"width":1,"height":1},"opacity":0,"edgeAntialiasingMask":251658240,"height":540,"hidden":false,"anchorPoint":{"pointX":0.5,"pointY":0.5}},"layers":[]}]}]},"effects":[],"duration":1.200000047683716,"type":"transition","name":"com.apple.iWork.Keynote.BLTFadeThruColor","objectID":"0"}],"automaticPlay":true,"hyperlinks":[],"accessibility":[{"text":"添加标题","targetRectangle":{"y":316.6277856826782,"x":742.7734560966492,"width":72,"height":25}},{"text":"产品四","targetRectangle":{"y":247.4201929361861,"x":774.0782623291016,"width":54,"height":25}},{"text":"产品一","targetRectangle":{"y":248.178541401152,"x":129.8272476196289,"width":54,"height":25}},{"text":"添加标题","targetRectangle":{"y":316.6277856826782,"x":520.6785769462585,"width":72,"height":25}},{"text":"image15.jpg","targetRectangle":{"y":150.4838562011719,"x":495.6670837402344,"width":165.8125152587891,"height":109.4362945556641}},{"text":"单击此处添加对图片的说明文字单击此处添加对图片的说明文字.","targetRectangle":{"y":359.5577058792114,"x":276.0326814651489,"width":168,"height":90}},{"text":"image14.jpg","targetRectangle":{"y":146.3364562988281,"x":281.8021240234375,"width":164.5102386474609,"height":108.5558319091797}},{"text":"产品三","targetRectangle":{"y":247.4202692301315,"x":551.9833831787109,"width":54,"height":25}},{"text":"04","targetRectangle":{"y":76.65866303443909,"x":94.06417417526245,"width":18,"height":23}},{"text":"image14.jpg","targetRectangle":{"y":146.3364562988281,"x":717.761962890625,"width":163.6952819824219,"height":108.5558319091797}},{"text":"点击输入标题 ","targetRectangle":{"y":65.95228338241577,"x":136.7823576927185,"width":200.890625,"height":45}},{"text":"单击此处添加对图片的说明文字单击此处添加对图片的说明文字.","targetRectangle":{"y":359.8055086135864,"x":721.3933992385864,"width":168,"height":90}},{"text":"添加标题","targetRectangle":{"y":316.6277856826782,"x":94.99598264694214,"width":72,"height":25}},{"text":"单击此处添加对图片的说明文字单击此处添加对图片的说明文字.","targetRectangle":{"y":357.5914278030396,"x":67.89755725860596,"width":168,"height":90}},{"text":"产品二","targetRectangle":{"y":248.178541401152,"x":338.1184234619141,"width":54,"height":25}},{"text":"单击此处添加对图片的说明文字单击此处添加对图片的说明文字.","targetRectangle":{"y":359.8055086135864,"x":490.0537691116333,"width":168,"height":90}},{"text":"image15.jpg","targetRectangle":{"y":150.4838562011719,"x":74.33102416992188,"width":165.8125152587891,"height":109.4362945556641}},{"text":"1.1","targetRectangle":{"y":3.224959850311279,"x":77.72503805160522,"width":37.8515625,"height":48}},{"text":"添加标题","targetRectangle":{"y":316.6277856826782,"x":304.5639224052429,"width":72,"height":25}}],"baseLayer":{"animations":[],"initialState":{"affineTransform":[1,0,0,1,0,0],"masksToBounds":false,"rotation":0,"scale":1,"position":{"pointX":480,"pointY":270},"width":960,"sublayerTransform":[1,0,0,0,0,1,0,0,0,0,1,0,0,0,0,1],"contentsRect":{"y":0,"x":0,"width":1,"height":1},"opacity":1,"edgeAntialiasingMask":251658240,"height":540,"hidden":false,"anchorPoint":{"pointX":0.5,"pointY":0.5}},"objectID":"0","layers":[{"animations":[],"initialState":{"affineTransform":[1,0,0,1,0,0],"masksToBounds":false,"rotation":0,"scale":1,"position":{"pointX":480,"pointY":270},"width":960,"sublayerTransform":[1,0,0,0,0,1,0,0,0,0,1,-0.0007001582493355197,0,0,0,1],"contentsRect":{"y":0,"x":0,"width":1,"height":1},"opacity":1,"edgeAntialiasingMask":251658240,"height":540,"hidden":false,"anchorPoint":{"pointX":0.5,"pointY":0.5}},"layers":[{"animations":[],"layers":[],"texturedRectangle":{"isBackgroundTexture":false,"singleTextureOpacity":1,"textureType":0,"textBaseline":0,"textXHeight":0,"isVerticalText":false},"initialState":{"affineTransform":[1,0,0,1,0,0],"masksToBounds":false,"rotation":0,"scale":1,"position":{"pointX":480,"pointY":270},"width":960,"sublayerTransform":[1,0,0,0,0,1,0,0,0,0,1,0,0,0,0,1],"contentsRect":{"y":0,"x":0,"width":1,"height":1},"opacity":1,"edgeAntialiasingMask":0,"height":540,"hidden":false,"anchorPoint":{"pointX":0.5,"pointY":0.5}},"texture":"8D7873D41F2F1E842D8E192A569B4856"}]}]}}]}